{ "definition" : { "accountID" : 24252 , "profileID" : "zzDVIQJKL88" , "ID" : "dTCg52wKh88" , "name" : "Article Interactions" , "description" : "" , "language" : null , "timezone" : "UTC 1" , "dimensions" : [ { "ID" : "H5W9vpZKh88" , "name" : "Article Name" } ] , "measures" : [ { "name" : "ArticleViews" , "ID" : "L0KUxkILh88" , "columnID" : 0 , "measureFormatType" : null },{ "name" : "ArticleImpressions" , "ID" : "TLYDknNkh88" , "columnID" : 1 , "measureFormatType" : null },{ "name" : "ArticleLike" , "ID" : "iLoM5Mxkh88" , "columnID" : 2 , "measureFormatType" : null },{ "name" : "ArticlePost" , "ID" : "XAGH035Lh88" , "columnID" : 3 , "measureFormatType" : null },{ "name" : "ArticleSave" , "ID" : "r6QLTI8Lh88" , "columnID" : 4 , "measureFormatType" : null },{ "name" : "ArticleUnlike" , "ID" : "7eQnQYELh88" , "columnID" : 5 , "measureFormatType" : null },{ "name" : "ArticleUnsave" , "ID" : "QP84DxGLh88" , "columnID" : 6 , "measureFormatType" : null },{ "name" : "ArticleSendbyEmail" , "ID" : "ZaHCa0CLh88" , "columnID" : 7 , "measureFormatType" : null } ] } ,"data" : [ { "period" : "Day" , "start_date" : "2021-10-01" , "end_date" : "2021-10-31" , "attributes" : {  } , "measures" : { "ArticleViews" : 122 , "ArticleImpressions" : 123 , "ArticleLike" : 60 , "ArticlePost" : 31 , "ArticleSave" : 31 , "ArticleUnlike" : 60 , "ArticleUnsave" : 30 , "ArticleSendbyEmail" : 31 } , "SubRows" : [  { "Benefit Updates" : {  "attributes" : {  } , "measures" : { "ArticleViews" : 31 , "ArticleImpressions" : 62 , "ArticleLike" : 30 , "ArticlePost" : 0 , "ArticleSave" : 0 , "ArticleUnlike" : 30 , "ArticleUnsave" : 0 , "ArticleSendbyEmail" : 0 } , "SubRows" : null }  , "Engineering News" : {  "attributes" : {  } , "measures" : { "ArticleViews" : 30 , "ArticleImpressions" : 61 , "ArticleLike" : 0 , "ArticlePost" : 0 , "ArticleSave" : 0 , "ArticleUnlike" : 0 , "ArticleUnsave" : 0 , "ArticleSendbyEmail" : 0 } , "SubRows" : null }  , "Todays Morning News" : {  "attributes" : {  } , "measures" : { "ArticleViews" : 61 , "ArticleImpressions" : 0 , "ArticleLike" : 30 , "ArticlePost" : 31 , "ArticleSave" : 31 , "ArticleUnlike" : 30 , "ArticleUnsave" : 30 , "ArticleSendbyEmail" : 31 } , "SubRows" : null }  } ] } ] }