{ "definition" : { "accountID" : 24252 , "profileID" : "zzDVIQJKL88" , "ID" : "mow96iGgGh7" , "name" : "Device Types: Browsers" , "description" : "This report provide a view into the devices and browsers being used to view SharePoint." , "language" : null , "timezone" : "UTC 1" , "dimensions" : [ { "ID" : "5ZkzA0bDGh7" , "name" : "Device Type" },{ "ID" : "browser_hit" , "name" : "Browser" } ] , "measures" : [ { "name" : "Sessions" , "ID" : "Visits" , "columnID" : 0 , "measureFormatType" : null },{ "name" : "PageViews" , "ID" : "CAoNYspmFb5" , "columnID" : 1 , "measureFormatType" : null },{ "name" : "SinglePageViewSessions" , "ID" : "JP3fwtZ7DM6" , "columnID" : 3 , "measureFormatType" : null },{ "name" : "EntryPageSessions" , "ID" : "RDqgRX18DM6" , "columnID" : 4 , "measureFormatType" : null },{ "name" : "AvgViewTimeSec" , "ID" : "fC51LCSmFb5" , "columnID" : 5 , "measureFormatType" : null },{ "name" : "AvgSessionDurationMins" , "ID" : "9VUp0ikQJb5" , "columnID" : 6 , "measureFormatType" : null },{ "name" : "BounceRate" , "ID" : "HzywuEAkVM6" , "columnID" : 2 , "measureFormatType" : "percent" },{ "name" : "ViewsperSession" , "ID" : "vxCAdAZdMh7" , "columnID" : 7 , "measureFormatType" : "numeric" } ] } ,"data" : [ { "period" : "Day" , "start_date" : "2021-10-01" , "end_date" : "2021-10-31" , "attributes" : {  } , "measures" : { "Sessions" : 1063 , "PageViews" : 3244 , "SinglePageViewSessions" : 243 , "EntryPageSessions" : 842 , "AvgViewTimeSec" : 145.897727272727 , "AvgSessionDurationMins" : 6.32060201975541 , "BounceRate" : 28.8598574821853 , "ViewsperSession" : 3.05174035747883 } , "SubRows" : [  { "Mobile Phone" : {  "attributes" : {  } , "measures" : { "Sessions" : 93 , "PageViews" : 155 , "SinglePageViewSessions" : 62 , "EntryPageSessions" : 93 , "AvgViewTimeSec" : 78 , "AvgSessionDurationMins" : 0.866666666666667 , "BounceRate" : 66.6666666666667 , "ViewsperSession" : 1.66666666666667 } , "SubRows" : { "Safari" : {  "attributes" : {  } , "measures" : { "Sessions" : 62 , "PageViews" : 62 , "SinglePageViewSessions" : 62 , "EntryPageSessions" : 62 , "AvgViewTimeSec" : null , "AvgSessionDurationMins" : 0 , "BounceRate" : 100 , "ViewsperSession" : 1 } , "SubRows" : null }  , "Chrome Mobile" : {  "attributes" : {  } , "measures" : { "Sessions" : 31 , "PageViews" : 93 , "SinglePageViewSessions" : 0 , "EntryPageSessions" : 31 , "AvgViewTimeSec" : 78 , "AvgSessionDurationMins" : 2.6 , "BounceRate" : 0 , "ViewsperSession" : 3 } , "SubRows" : null }  } } , "Desktop" : {  "attributes" : {  } , "measures" : { "Sessions" : 970 , "PageViews" : 3089 , "SinglePageViewSessions" : 181 , "EntryPageSessions" : 749 , "AvgViewTimeSec" : 147.866697848457 , "AvgSessionDurationMins" : 6.8435051 , "BounceRate" : 24.1655540720961 , "ViewsperSession" : 3.18453608247423 } , "SubRows" : { "Google Chrome" : {  "attributes" : {  } , "measures" : { "Sessions" : 321 , "PageViews" : 1233 , "SinglePageViewSessions" : 56 , "EntryPageSessions" : 230 , "AvgViewTimeSec" : 202.477426636569 , "AvgSessionDurationMins" : 13.7162512429907 , "BounceRate" : 24.3478260869565 , "ViewsperSession" : 3.8411214953271 } , "SubRows" : null }  , "Firefox" : {  "attributes" : {  } , "measures" : { "Sessions" : 312 , "PageViews" : 674 , "SinglePageViewSessions" : 32 , "EntryPageSessions" : 184 , "AvgViewTimeSec" : 159.823754789272 , "AvgSessionDurationMins" : 4.89369653846154 , "BounceRate" : 17.3913043478261 , "ViewsperSession" : 2.16025641025641 } , "SubRows" : null }  , "Microsoft Internet Explorer" : {  "attributes" : {  } , "measures" : { "Sessions" : 304 , "PageViews" : 910 , "SinglePageViewSessions" : 94 , "EntryPageSessions" : 304 , "AvgViewTimeSec" : 82.896174863388 , "AvgSessionDurationMins" : 2.56907890131579 , "BounceRate" : 30.9210526315789 , "ViewsperSession" : 2.99342105263158 } , "SubRows" : null }  , "Microsoft Edge" : {  "attributes" : {  } , "measures" : { "Sessions" : 94 , "PageViews" : 182 , "SinglePageViewSessions" : 0 , "EntryPageSessions" : 31 , "AvgViewTimeSec" : 24.3196721311475 , "AvgSessionDurationMins" : 4.94485815957447 , "BounceRate" : 0 , "ViewsperSession" : 1.93617021276596 } , "SubRows" : null }  , "Microsoft Chromium Edge" : {  "attributes" : {  } , "measures" : { "Sessions" : 31 , "PageViews" : 90 , "SinglePageViewSessions" : 0 , "EntryPageSessions" : 0 , "AvgViewTimeSec" : 82.0169491525424 , "AvgSessionDurationMins" : 38.8521505483871 , "BounceRate" : null , "ViewsperSession" : 2.90322580645161 } , "SubRows" : null }  } } } ] } ] }