{ "definition" : { "accountID" : 24252 , "profileID" : "zzDVIQJKL88" , "ID" : "xwtRiYhsKh7" , "name" : "Site Names: Web Parts" , "description" : "This report provides a view into the web parts interactions by site collection in SharePoint." , "language" : null , "timezone" : "UTC 1" , "dimensions" : [ { "ID" : "w3LCMjIMFh7" , "name" : "Site Name" },{ "ID" : "qqYAV55WSc7" , "name" : "Web Part Name" } ] , "measures" : [ { "name" : "Sessions" , "ID" : "Visits" , "columnID" : 0 , "measureFormatType" : null },{ "name" : "PageViews" , "ID" : "CAoNYspmFb5" , "columnID" : 1 , "measureFormatType" : null },{ "name" : "SinglePageViewSessions" , "ID" : "JP3fwtZ7DM6" , "columnID" : 3 , "measureFormatType" : null },{ "name" : "EntryPageSessions" , "ID" : "RDqgRX18DM6" , "columnID" : 4 , "measureFormatType" : null },{ "name" : "AvgViewTimeSec" , "ID" : "fC51LCSmFb5" , "columnID" : 5 , "measureFormatType" : null },{ "name" : "BounceRate" , "ID" : "HzywuEAkVM6" , "columnID" : 2 , "measureFormatType" : "percent" },{ "name" : "ViewsperSession" , "ID" : "ehaxEG7dMh7" , "columnID" : 6 , "measureFormatType" : "numeric" } ] } ,"data" : [ { "period" : "Day" , "start_date" : "2021-10-01" , "end_date" : "2021-10-31" , "attributes" : {  } , "measures" : { "Sessions" : 1235 , "PageViews" : 21475 , "SinglePageViewSessions" : 243 , "EntryPageSessions" : 8500 , "AvgViewTimeSec" : 123.784884621341 , "BounceRate" : 2.85882352941176 , "ViewsperSession" : 17.3886639676113 } , "SubRows" : [  { "Blog Site" : {  "attributes" : {  } , "measures" : { "Sessions" : 155 , "PageViews" : 3708 , "SinglePageViewSessions" : 31 , "EntryPageSessions" : 1488 , "AvgViewTimeSec" : 22.1783439490446 , "BounceRate" : 2.08333333333333 , "ViewsperSession" : 23.9225806451613 } , "SubRows" : { "People I am following" : {  "attributes" : {  } , "measures" : { "Sessions" : 155 , "PageViews" : 309 , "SinglePageViewSessions" : 31 , "EntryPageSessions" : 124 , "AvgViewTimeSec" : 22.1783439490446 , "BounceRate" : 25 , "ViewsperSession" : 1.99354838709677 } , "SubRows" : null }  , "People Search" : {  "attributes" : {  } , "measures" : { "Sessions" : 155 , "PageViews" : 309 , "SinglePageViewSessions" : 31 , "EntryPageSessions" : 124 , "AvgViewTimeSec" : 22.1783439490446 , "BounceRate" : 25 , "ViewsperSession" : 1.99354838709677 } , "SubRows" : null }  , "Location Navigation" : {  "attributes" : {  } , "measures" : { "Sessions" : 155 , "PageViews" : 309 , "SinglePageViewSessions" : 31 , "EntryPageSessions" : 124 , "AvgViewTimeSec" : 22.1783439490446 , "BounceRate" : 25 , "ViewsperSession" : 1.99354838709677 } , "SubRows" : null }  , "Yammer" : {  "attributes" : {  } , "measures" : { "Sessions" : 155 , "PageViews" : 309 , "SinglePageViewSessions" : 31 , "EntryPageSessions" : 124 , "AvgViewTimeSec" : 22.1783439490446 , "BounceRate" : 25 , "ViewsperSession" : 1.99354838709677 } , "SubRows" : null }  , "iConnect" : {  "attributes" : {  } , "measures" : { "Sessions" : 155 , "PageViews" : 309 , "SinglePageViewSessions" : 31 , "EntryPageSessions" : 124 , "AvgViewTimeSec" : 22.1783439490446 , "BounceRate" : 25 , "ViewsperSession" : 1.99354838709677 } , "SubRows" : null }  , "Stock" : {  "attributes" : {  } , "measures" : { "Sessions" : 155 , "PageViews" : 309 , "SinglePageViewSessions" : 31 , "EntryPageSessions" : 124 , "AvgViewTimeSec" : 22.1783439490446 , "BounceRate" : 25 , "ViewsperSession" : 1.99354838709677 } , "SubRows" : null }  , "Slider" : {  "attributes" : {  } , "measures" : { "Sessions" : 155 , "PageViews" : 309 , "SinglePageViewSessions" : 31 , "EntryPageSessions" : 124 , "AvgViewTimeSec" : 22.1783439490446 , "BounceRate" : 25 , "ViewsperSession" : 1.99354838709677 } , "SubRows" : null }  , "Sites I am following" : {  "attributes" : {  } , "measures" : { "Sessions" : 155 , "PageViews" : 309 , "SinglePageViewSessions" : 31 , "EntryPageSessions" : 124 , "AvgViewTimeSec" : 22.1783439490446 , "BounceRate" : 25 , "ViewsperSession" : 1.99354838709677 } , "SubRows" : null }  , "Home page script" : {  "attributes" : {  } , "measures" : { "Sessions" : 155 , "PageViews" : 309 , "SinglePageViewSessions" : 31 , "EntryPageSessions" : 124 , "AvgViewTimeSec" : 22.1783439490446 , "BounceRate" : 25 , "ViewsperSession" : 1.99354838709677 } , "SubRows" : null }  , "Script Editor" : {  "attributes" : {  } , "measures" : { "Sessions" : 155 , "PageViews" : 309 , "SinglePageViewSessions" : 31 , "EntryPageSessions" : 124 , "AvgViewTimeSec" : 22.1783439490446 , "BounceRate" : 25 , "ViewsperSession" : 1.99354838709677 } , "SubRows" : null }  , "Small Input Search Box" : {  "attributes" : {  } , "measures" : { "Sessions" : 155 , "PageViews" : 309 , "SinglePageViewSessions" : 31 , "EntryPageSessions" : 124 , "AvgViewTimeSec" : 22.1783439490446 , "BounceRate" : 25 , "ViewsperSession" : 1.99354838709677 } , "SubRows" : null }  , "Featured Links" : {  "attributes" : {  } , "measures" : { "Sessions" : 155 , "PageViews" : 309 , "SinglePageViewSessions" : 31 , "EntryPageSessions" : 124 , "AvgViewTimeSec" : 22.1783439490446 , "BounceRate" : 25 , "ViewsperSession" : 1.99354838709677 } , "SubRows" : null }  } } , "BlogSite" : {  "attributes" : {  } , "measures" : { "Sessions" : 60 , "PageViews" : 720 , "SinglePageViewSessions" : 30 , "EntryPageSessions" : 480 , "AvgViewTimeSec" : 20 , "BounceRate" : 6.25 , "ViewsperSession" : 12 } , "SubRows" : { "Small Input Search Box" : {  "attributes" : {  } , "measures" : { "Sessions" : 60 , "PageViews" : 60 , "SinglePageViewSessions" : 30 , "EntryPageSessions" : 40 , "AvgViewTimeSec" : 20 , "BounceRate" : 75 , "ViewsperSession" : 1 } , "SubRows" : null }  , "Featured Links" : {  "attributes" : {  } , "measures" : { "Sessions" : 60 , "PageViews" : 60 , "SinglePageViewSessions" : 30 , "EntryPageSessions" : 40 , "AvgViewTimeSec" : 20 , "BounceRate" : 75 , "ViewsperSession" : 1 } , "SubRows" : null }  , "Home page script" : {  "attributes" : {  } , "measures" : { "Sessions" : 60 , "PageViews" : 60 , "SinglePageViewSessions" : 30 , "EntryPageSessions" : 40 , "AvgViewTimeSec" : 20 , "BounceRate" : 75 , "ViewsperSession" : 1 } , "SubRows" : null }  , "Slider" : {  "attributes" : {  } , "measures" : { "Sessions" : 60 , "PageViews" : 60 , "SinglePageViewSessions" : 30 , "EntryPageSessions" : 40 , "AvgViewTimeSec" : 20 , "BounceRate" : 75 , "ViewsperSession" : 1 } , "SubRows" : null }  , "People Search" : {  "attributes" : {  } , "measures" : { "Sessions" : 60 , "PageViews" : 60 , "SinglePageViewSessions" : 30 , "EntryPageSessions" : 40 , "AvgViewTimeSec" : 20 , "BounceRate" : 75 , "ViewsperSession" : 1 } , "SubRows" : null }  , "Yammer" : {  "attributes" : {  } , "measures" : { "Sessions" : 60 , "PageViews" : 60 , "SinglePageViewSessions" : 30 , "EntryPageSessions" : 40 , "AvgViewTimeSec" : 20 , "BounceRate" : 75 , "ViewsperSession" : 1 } , "SubRows" : null }  , "Sites I am following" : {  "attributes" : {  } , "measures" : { "Sessions" : 60 , "PageViews" : 60 , "SinglePageViewSessions" : 30 , "EntryPageSessions" : 40 , "AvgViewTimeSec" : 20 , "BounceRate" : 75 , "ViewsperSession" : 1 } , "SubRows" : null }  , "Location Navigation" : {  "attributes" : {  } , "measures" : { "Sessions" : 60 , "PageViews" : 60 , "SinglePageViewSessions" : 30 , "EntryPageSessions" : 40 , "AvgViewTimeSec" : 20 , "BounceRate" : 75 , "ViewsperSession" : 1 } , "SubRows" : null }  , "Stock" : {  "attributes" : {  } , "measures" : { "Sessions" : 60 , "PageViews" : 60 , "SinglePageViewSessions" : 30 , "EntryPageSessions" : 40 , "AvgViewTimeSec" : 20 , "BounceRate" : 75 , "ViewsperSession" : 1 } , "SubRows" : null }  , "Script Editor" : {  "attributes" : {  } , "measures" : { "Sessions" : 60 , "PageViews" : 60 , "SinglePageViewSessions" : 30 , "EntryPageSessions" : 40 , "AvgViewTimeSec" : 20 , "BounceRate" : 75 , "ViewsperSession" : 1 } , "SubRows" : null }  , "People I am following" : {  "attributes" : {  } , "measures" : { "Sessions" : 60 , "PageViews" : 60 , "SinglePageViewSessions" : 30 , "EntryPageSessions" : 40 , "AvgViewTimeSec" : 20 , "BounceRate" : 75 , "ViewsperSession" : 1 } , "SubRows" : null }  , "iConnect" : {  "attributes" : {  } , "measures" : { "Sessions" : 60 , "PageViews" : 60 , "SinglePageViewSessions" : 30 , "EntryPageSessions" : 40 , "AvgViewTimeSec" : 20 , "BounceRate" : 75 , "ViewsperSession" : 1 } , "SubRows" : null }  } } , "Client Services" : {  "attributes" : {  } , "measures" : { "Sessions" : 62 , "PageViews" : 1185 , "SinglePageViewSessions" : 31 , "EntryPageSessions" : 735 , "AvgViewTimeSec" : 12.8481012658228 , "BounceRate" : 4.21768707482993 , "ViewsperSession" : 19.1129032258065 } , "SubRows" : { "Script Editor" : {  "attributes" : {  } , "measures" : { "Sessions" : 62 , "PageViews" : 153 , "SinglePageViewSessions" : 31 , "EntryPageSessions" : 63 , "AvgViewTimeSec" : 11.5294117647059 , "BounceRate" : 49.2063492063492 , "ViewsperSession" : 2.46774193548387 } , "SubRows" : null }  , "Stock" : {  "attributes" : {  } , "measures" : { "Sessions" : 62 , "PageViews" : 91 , "SinglePageViewSessions" : 31 , "EntryPageSessions" : 61 , "AvgViewTimeSec" : 13.3333333333333 , "BounceRate" : 50.8196721311475 , "ViewsperSession" : 1.46774193548387 } , "SubRows" : null }  , "Featured Links" : {  "attributes" : {  } , "measures" : { "Sessions" : 62 , "PageViews" : 91 , "SinglePageViewSessions" : 31 , "EntryPageSessions" : 61 , "AvgViewTimeSec" : 13.3333333333333 , "BounceRate" : 50.8196721311475 , "ViewsperSession" : 1.46774193548387 } , "SubRows" : null }  , "Sites I am following" : {  "attributes" : {  } , "measures" : { "Sessions" : 62 , "PageViews" : 91 , "SinglePageViewSessions" : 31 , "EntryPageSessions" : 61 , "AvgViewTimeSec" : 13.3333333333333 , "BounceRate" : 50.8196721311475 , "ViewsperSession" : 1.46774193548387 } , "SubRows" : null }  , "People Search" : {  "attributes" : {  } , "measures" : { "Sessions" : 62 , "PageViews" : 91 , "SinglePageViewSessions" : 31 , "EntryPageSessions" : 61 , "AvgViewTimeSec" : 13.3333333333333 , "BounceRate" : 50.8196721311475 , "ViewsperSession" : 1.46774193548387 } , "SubRows" : null }  , "Home page script" : {  "attributes" : {  } , "measures" : { "Sessions" : 62 , "PageViews" : 91 , "SinglePageViewSessions" : 31 , "EntryPageSessions" : 61 , "AvgViewTimeSec" : 13.3333333333333 , "BounceRate" : 50.8196721311475 , "ViewsperSession" : 1.46774193548387 } , "SubRows" : null }  , "iConnect" : {  "attributes" : {  } , "measures" : { "Sessions" : 62 , "PageViews" : 91 , "SinglePageViewSessions" : 31 , "EntryPageSessions" : 61 , "AvgViewTimeSec" : 13.3333333333333 , "BounceRate" : 50.8196721311475 , "ViewsperSession" : 1.46774193548387 } , "SubRows" : null }  , "People I am following" : {  "attributes" : {  } , "measures" : { "Sessions" : 62 , "PageViews" : 91 , "SinglePageViewSessions" : 31 , "EntryPageSessions" : 61 , "AvgViewTimeSec" : 13.3333333333333 , "BounceRate" : 50.8196721311475 , "ViewsperSession" : 1.46774193548387 } , "SubRows" : null }  , "Location Navigation" : {  "attributes" : {  } , "measures" : { "Sessions" : 62 , "PageViews" : 91 , "SinglePageViewSessions" : 31 , "EntryPageSessions" : 61 , "AvgViewTimeSec" : 13.3333333333333 , "BounceRate" : 50.8196721311475 , "ViewsperSession" : 1.46774193548387 } , "SubRows" : null }  , "Small Input Search Box" : {  "attributes" : {  } , "measures" : { "Sessions" : 62 , "PageViews" : 122 , "SinglePageViewSessions" : 31 , "EntryPageSessions" : 62 , "AvgViewTimeSec" : 12.0338983050847 , "BounceRate" : 50 , "ViewsperSession" : 1.96774193548387 } , "SubRows" : null }  , "Yammer" : {  "attributes" : {  } , "measures" : { "Sessions" : 62 , "PageViews" : 91 , "SinglePageViewSessions" : 31 , "EntryPageSessions" : 61 , "AvgViewTimeSec" : 13.3333333333333 , "BounceRate" : 50.8196721311475 , "ViewsperSession" : 1.46774193548387 } , "SubRows" : null }  , "Slider" : {  "attributes" : {  } , "measures" : { "Sessions" : 62 , "PageViews" : 91 , "SinglePageViewSessions" : 31 , "EntryPageSessions" : 61 , "AvgViewTimeSec" : 13.3333333333333 , "BounceRate" : 50.8196721311475 , "ViewsperSession" : 1.46774193548387 } , "SubRows" : null }  } } , "CommonConnection" : {  "attributes" : {  } , "measures" : { "Sessions" : 29 , "PageViews" : 203 , "SinglePageViewSessions" : 0 , "EntryPageSessions" : 0 , "AvgViewTimeSec" : 4.06896551724138 , "BounceRate" : null , "ViewsperSession" : 7 } , "SubRows" : { "Quick links" : {  "attributes" : {  } , "measures" : { "Sessions" : 29 , "PageViews" : 29 , "SinglePageViewSessions" : 0 , "EntryPageSessions" : 0 , "AvgViewTimeSec" : 4.06896551724138 , "BounceRate" : null , "ViewsperSession" : 1 } , "SubRows" : null }  , "Hero" : {  "attributes" : {  } , "measures" : { "Sessions" : 29 , "PageViews" : 58 , "SinglePageViewSessions" : 0 , "EntryPageSessions" : 0 , "AvgViewTimeSec" : 4.06896551724138 , "BounceRate" : null , "ViewsperSession" : 2 } , "SubRows" : null }  , "Site activity" : {  "attributes" : {  } , "measures" : { "Sessions" : 29 , "PageViews" : 29 , "SinglePageViewSessions" : 0 , "EntryPageSessions" : 0 , "AvgViewTimeSec" : 4.06896551724138 , "BounceRate" : null , "ViewsperSession" : 1 } , "SubRows" : null }  , "Document library" : {  "attributes" : {  } , "measures" : { "Sessions" : 29 , "PageViews" : 29 , "SinglePageViewSessions" : 0 , "EntryPageSessions" : 0 , "AvgViewTimeSec" : 4.06896551724138 , "BounceRate" : null , "ViewsperSession" : 1 } , "SubRows" : null }  , "Lista" : {  "attributes" : {  } , "measures" : { "Sessions" : 29 , "PageViews" : 29 , "SinglePageViewSessions" : 0 , "EntryPageSessions" : 0 , "AvgViewTimeSec" : 4.06896551724138 , "BounceRate" : null , "ViewsperSession" : 1 } , "SubRows" : null }  , "News" : {  "attributes" : {  } , "measures" : { "Sessions" : 29 , "PageViews" : 29 , "SinglePageViewSessions" : 0 , "EntryPageSessions" : 0 , "AvgViewTimeSec" : 4.06896551724138 , "BounceRate" : null , "ViewsperSession" : 1 } , "SubRows" : null }  } } , "Company News" : {  "attributes" : {  } , "measures" : { "Sessions" : 25 , "PageViews" : 25 , "SinglePageViewSessions" : 0 , "EntryPageSessions" : 0 , "AvgViewTimeSec" : null , "BounceRate" : null , "ViewsperSession" : 1 } , "SubRows" : { "Search SearchBox" : {  "attributes" : {  } , "measures" : { "Sessions" : 25 , "PageViews" : 25 , "SinglePageViewSessions" : 0 , "EntryPageSessions" : 0 , "AvgViewTimeSec" : null , "BounceRate" : null , "ViewsperSession" : 1 } , "SubRows" : null }  } } , "CorpComms" : {  "attributes" : {  } , "measures" : { "Sessions" : 31 , "PageViews" : 0 , "SinglePageViewSessions" : 0 , "EntryPageSessions" : 0 , "AvgViewTimeSec" : null , "BounceRate" : null , "ViewsperSession" : 0 } , "SubRows" : { "Stream" : {  "attributes" : {  } , "measures" : { "Sessions" : 31 , "PageViews" : 0 , "SinglePageViewSessions" : 0 , "EntryPageSessions" : 0 , "AvgViewTimeSec" : null , "BounceRate" : null , "ViewsperSession" : 0 } , "SubRows" : null }  } } , "corporate" : {  "attributes" : {  } , "measures" : { "Sessions" : 62 , "PageViews" : 847 , "SinglePageViewSessions" : 0 , "EntryPageSessions" : 434 , "AvgViewTimeSec" : 75.8403361344538 , "BounceRate" : 0 , "ViewsperSession" : 13.6612903225806 } , "SubRows" : { "News" : {  "attributes" : {  } , "measures" : { "Sessions" : 62 , "PageViews" : 121 , "SinglePageViewSessions" : 0 , "EntryPageSessions" : 62 , "AvgViewTimeSec" : 75.8403361344538 , "BounceRate" : 0 , "ViewsperSession" : 1.95161290322581 } , "SubRows" : null }  , "Site activity" : {  "attributes" : {  } , "measures" : { "Sessions" : 62 , "PageViews" : 121 , "SinglePageViewSessions" : 0 , "EntryPageSessions" : 62 , "AvgViewTimeSec" : 75.8403361344538 , "BounceRate" : 0 , "ViewsperSession" : 1.95161290322581 } , "SubRows" : null }  , "Lista" : {  "attributes" : {  } , "measures" : { "Sessions" : 62 , "PageViews" : 121 , "SinglePageViewSessions" : 0 , "EntryPageSessions" : 62 , "AvgViewTimeSec" : 75.8403361344538 , "BounceRate" : 0 , "ViewsperSession" : 1.95161290322581 } , "SubRows" : null }  , "Document library" : {  "attributes" : {  } , "measures" : { "Sessions" : 62 , "PageViews" : 121 , "SinglePageViewSessions" : 0 , "EntryPageSessions" : 62 , "AvgViewTimeSec" : 75.8403361344538 , "BounceRate" : 0 , "ViewsperSession" : 1.95161290322581 } , "SubRows" : null }  , "Hero" : {  "attributes" : {  } , "measures" : { "Sessions" : 62 , "PageViews" : 242 , "SinglePageViewSessions" : 0 , "EntryPageSessions" : 124 , "AvgViewTimeSec" : 75.8403361344538 , "BounceRate" : 0 , "ViewsperSession" : 3.90322580645161 } , "SubRows" : null }  , "Quick links" : {  "attributes" : {  } , "measures" : { "Sessions" : 62 , "PageViews" : 121 , "SinglePageViewSessions" : 0 , "EntryPageSessions" : 62 , "AvgViewTimeSec" : 75.8403361344538 , "BounceRate" : 0 , "ViewsperSession" : 1.95161290322581 } , "SubRows" : null }  } } , "Employee Services" : {  "attributes" : {  } , "measures" : { "Sessions" : 31 , "PageViews" : 985 , "SinglePageViewSessions" : 0 , "EntryPageSessions" : 0 , "AvgViewTimeSec" : 40.5840807174888 , "BounceRate" : null , "ViewsperSession" : 31.7741935483871 } , "SubRows" : { "Refinement" : {  "attributes" : {  } , "measures" : { "Sessions" : 31 , "PageViews" : 153 , "SinglePageViewSessions" : 0 , "EntryPageSessions" : 0 , "AvgViewTimeSec" : 14.8770491803279 , "BounceRate" : null , "ViewsperSession" : 4.93548387096774 } , "SubRows" : null }  , "Script Editor" : {  "attributes" : {  } , "measures" : { "Sessions" : 31 , "PageViews" : 124 , "SinglePageViewSessions" : 0 , "EntryPageSessions" : 0 , "AvgViewTimeSec" : 60.8548387096774 , "BounceRate" : null , "ViewsperSession" : 4 } , "SubRows" : null }  , "Search Box" : {  "attributes" : {  } , "measures" : { "Sessions" : 31 , "PageViews" : 124 , "SinglePageViewSessions" : 0 , "EntryPageSessions" : 0 , "AvgViewTimeSec" : 60.8548387096774 , "BounceRate" : null , "ViewsperSession" : 4 } , "SubRows" : null }  , "Promoted Links Policies" : {  "attributes" : {  } , "measures" : { "Sessions" : 31 , "PageViews" : 124 , "SinglePageViewSessions" : 0 , "EntryPageSessions" : 0 , "AvgViewTimeSec" : 60.8548387096774 , "BounceRate" : null , "ViewsperSession" : 4 } , "SubRows" : null }  , "Search Results" : {  "attributes" : {  } , "measures" : { "Sessions" : 31 , "PageViews" : 153 , "SinglePageViewSessions" : 0 , "EntryPageSessions" : 0 , "AvgViewTimeSec" : 14.8770491803279 , "BounceRate" : null , "ViewsperSession" : 4.93548387096774 } , "SubRows" : null }  , "Small Input Search Box" : {  "attributes" : {  } , "measures" : { "Sessions" : 31 , "PageViews" : 307 , "SinglePageViewSessions" : 0 , "EntryPageSessions" : 0 , "AvgViewTimeSec" : 35.9891304347826 , "BounceRate" : null , "ViewsperSession" : 9.90322580645161 } , "SubRows" : null }  } } , "Engineering" : {  "attributes" : {  } , "measures" : { "Sessions" : 31 , "PageViews" : 732 , "SinglePageViewSessions" : 1 , "EntryPageSessions" : 372 , "AvgViewTimeSec" : 119 , "BounceRate" : 0.268817204301075 , "ViewsperSession" : 23.6129032258065 } , "SubRows" : { "Featured Links" : {  "attributes" : {  } , "measures" : { "Sessions" : 31 , "PageViews" : 61 , "SinglePageViewSessions" : 1 , "EntryPageSessions" : 31 , "AvgViewTimeSec" : 119 , "BounceRate" : 3.2258064516129 , "ViewsperSession" : 1.96774193548387 } , "SubRows" : null }  , "People Search" : {  "attributes" : {  } , "measures" : { "Sessions" : 31 , "PageViews" : 61 , "SinglePageViewSessions" : 1 , "EntryPageSessions" : 31 , "AvgViewTimeSec" : 119 , "BounceRate" : 3.2258064516129 , "ViewsperSession" : 1.96774193548387 } , "SubRows" : null }  , "Stock" : {  "attributes" : {  } , "measures" : { "Sessions" : 31 , "PageViews" : 61 , "SinglePageViewSessions" : 1 , "EntryPageSessions" : 31 , "AvgViewTimeSec" : 119 , "BounceRate" : 3.2258064516129 , "ViewsperSession" : 1.96774193548387 } , "SubRows" : null }  , "Script Editor" : {  "attributes" : {  } , "measures" : { "Sessions" : 31 , "PageViews" : 61 , "SinglePageViewSessions" : 1 , "EntryPageSessions" : 31 , "AvgViewTimeSec" : 119 , "BounceRate" : 3.2258064516129 , "ViewsperSession" : 1.96774193548387 } , "SubRows" : null }  , "Yammer" : {  "attributes" : {  } , "measures" : { "Sessions" : 31 , "PageViews" : 61 , "SinglePageViewSessions" : 1 , "EntryPageSessions" : 31 , "AvgViewTimeSec" : 119 , "BounceRate" : 3.2258064516129 , "ViewsperSession" : 1.96774193548387 } , "SubRows" : null }  , "Location Navigation" : {  "attributes" : {  } , "measures" : { "Sessions" : 31 , "PageViews" : 61 , "SinglePageViewSessions" : 1 , "EntryPageSessions" : 31 , "AvgViewTimeSec" : 119 , "BounceRate" : 3.2258064516129 , "ViewsperSession" : 1.96774193548387 } , "SubRows" : null }  , "Small Input Search Box" : {  "attributes" : {  } , "measures" : { "Sessions" : 31 , "PageViews" : 61 , "SinglePageViewSessions" : 1 , "EntryPageSessions" : 31 , "AvgViewTimeSec" : 119 , "BounceRate" : 3.2258064516129 , "ViewsperSession" : 1.96774193548387 } , "SubRows" : null }  , "Sites I am following" : {  "attributes" : {  } , "measures" : { "Sessions" : 31 , "PageViews" : 61 , "SinglePageViewSessions" : 1 , "EntryPageSessions" : 31 , "AvgViewTimeSec" : 119 , "BounceRate" : 3.2258064516129 , "ViewsperSession" : 1.96774193548387 } , "SubRows" : null }  , "Home page script" : {  "attributes" : {  } , "measures" : { "Sessions" : 31 , "PageViews" : 61 , "SinglePageViewSessions" : 1 , "EntryPageSessions" : 31 , "AvgViewTimeSec" : 119 , "BounceRate" : 3.2258064516129 , "ViewsperSession" : 1.96774193548387 } , "SubRows" : null }  , "Slider" : {  "attributes" : {  } , "measures" : { "Sessions" : 31 , "PageViews" : 61 , "SinglePageViewSessions" : 1 , "EntryPageSessions" : 31 , "AvgViewTimeSec" : 119 , "BounceRate" : 3.2258064516129 , "ViewsperSession" : 1.96774193548387 } , "SubRows" : null }  , "iConnect" : {  "attributes" : {  } , "measures" : { "Sessions" : 31 , "PageViews" : 61 , "SinglePageViewSessions" : 1 , "EntryPageSessions" : 31 , "AvgViewTimeSec" : 119 , "BounceRate" : 3.2258064516129 , "ViewsperSession" : 1.96774193548387 } , "SubRows" : null }  , "People I am following" : {  "attributes" : {  } , "measures" : { "Sessions" : 31 , "PageViews" : 61 , "SinglePageViewSessions" : 1 , "EntryPageSessions" : 31 , "AvgViewTimeSec" : 119 , "BounceRate" : 3.2258064516129 , "ViewsperSession" : 1.96774193548387 } , "SubRows" : null }  } } , "Finance" : {  "attributes" : {  } , "measures" : { "Sessions" : 31 , "PageViews" : 372 , "SinglePageViewSessions" : 31 , "EntryPageSessions" : 372 , "AvgViewTimeSec" : null , "BounceRate" : 8.33333333333333 , "ViewsperSession" : 12 } , "SubRows" : { "Sites I am following" : {  "attributes" : {  } , "measures" : { "Sessions" : 31 , "PageViews" : 31 , "SinglePageViewSessions" : 31 , "EntryPageSessions" : 31 , "AvgViewTimeSec" : null , "BounceRate" : 100 , "ViewsperSession" : 1 } , "SubRows" : null }  , "Yammer" : {  "attributes" : {  } , "measures" : { "Sessions" : 31 , "PageViews" : 31 , "SinglePageViewSessions" : 31 , "EntryPageSessions" : 31 , "AvgViewTimeSec" : null , "BounceRate" : 100 , "ViewsperSession" : 1 } , "SubRows" : null }  , "Small Input Search Box" : {  "attributes" : {  } , "measures" : { "Sessions" : 31 , "PageViews" : 31 , "SinglePageViewSessions" : 31 , "EntryPageSessions" : 31 , "AvgViewTimeSec" : null , "BounceRate" : 100 , "ViewsperSession" : 1 } , "SubRows" : null }  , "Home page script" : {  "attributes" : {  } , "measures" : { "Sessions" : 31 , "PageViews" : 31 , "SinglePageViewSessions" : 31 , "EntryPageSessions" : 31 , "AvgViewTimeSec" : null , "BounceRate" : 100 , "ViewsperSession" : 1 } , "SubRows" : null }  , "iConnect" : {  "attributes" : {  } , "measures" : { "Sessions" : 31 , "PageViews" : 31 , "SinglePageViewSessions" : 31 , "EntryPageSessions" : 31 , "AvgViewTimeSec" : null , "BounceRate" : 100 , "ViewsperSession" : 1 } , "SubRows" : null }  , "Featured Links" : {  "attributes" : {  } , "measures" : { "Sessions" : 31 , "PageViews" : 31 , "SinglePageViewSessions" : 31 , "EntryPageSessions" : 31 , "AvgViewTimeSec" : null , "BounceRate" : 100 , "ViewsperSession" : 1 } , "SubRows" : null }  , "People Search" : {  "attributes" : {  } , "measures" : { "Sessions" : 31 , "PageViews" : 31 , "SinglePageViewSessions" : 31 , "EntryPageSessions" : 31 , "AvgViewTimeSec" : null , "BounceRate" : 100 , "ViewsperSession" : 1 } , "SubRows" : null }  , "Location Navigation" : {  "attributes" : {  } , "measures" : { "Sessions" : 31 , "PageViews" : 31 , "SinglePageViewSessions" : 31 , "EntryPageSessions" : 31 , "AvgViewTimeSec" : null , "BounceRate" : 100 , "ViewsperSession" : 1 } , "SubRows" : null }  , "Script Editor" : {  "attributes" : {  } , "measures" : { "Sessions" : 31 , "PageViews" : 31 , "SinglePageViewSessions" : 31 , "EntryPageSessions" : 31 , "AvgViewTimeSec" : null , "BounceRate" : 100 , "ViewsperSession" : 1 } , "SubRows" : null }  , "People I am following" : {  "attributes" : {  } , "measures" : { "Sessions" : 31 , "PageViews" : 31 , "SinglePageViewSessions" : 31 , "EntryPageSessions" : 31 , "AvgViewTimeSec" : null , "BounceRate" : 100 , "ViewsperSession" : 1 } , "SubRows" : null }  , "Stock" : {  "attributes" : {  } , "measures" : { "Sessions" : 31 , "PageViews" : 31 , "SinglePageViewSessions" : 31 , "EntryPageSessions" : 31 , "AvgViewTimeSec" : null , "BounceRate" : 100 , "ViewsperSession" : 1 } , "SubRows" : null }  , "Slider" : {  "attributes" : {  } , "measures" : { "Sessions" : 31 , "PageViews" : 31 , "SinglePageViewSessions" : 31 , "EntryPageSessions" : 31 , "AvgViewTimeSec" : null , "BounceRate" : 100 , "ViewsperSession" : 1 } , "SubRows" : null }  } } , "Human Resources" : {  "attributes" : {  } , "measures" : { "Sessions" : 57 , "PageViews" : 684 , "SinglePageViewSessions" : 32 , "EntryPageSessions" : 684 , "AvgViewTimeSec" : 91.7272727272727 , "BounceRate" : 4.67836257309941 , "ViewsperSession" : 12 } , "SubRows" : { "Featured Links" : {  "attributes" : {  } , "measures" : { "Sessions" : 57 , "PageViews" : 57 , "SinglePageViewSessions" : 32 , "EntryPageSessions" : 57 , "AvgViewTimeSec" : 91.7272727272727 , "BounceRate" : 56.140350877193 , "ViewsperSession" : 1 } , "SubRows" : null }  , "Stock" : {  "attributes" : {  } , "measures" : { "Sessions" : 57 , "PageViews" : 57 , "SinglePageViewSessions" : 32 , "EntryPageSessions" : 57 , "AvgViewTimeSec" : 91.7272727272727 , "BounceRate" : 56.140350877193 , "ViewsperSession" : 1 } , "SubRows" : null }  , "People Search" : {  "attributes" : {  } , "measures" : { "Sessions" : 57 , "PageViews" : 57 , "SinglePageViewSessions" : 32 , "EntryPageSessions" : 57 , "AvgViewTimeSec" : 91.7272727272727 , "BounceRate" : 56.140350877193 , "ViewsperSession" : 1 } , "SubRows" : null }  , "iConnect" : {  "attributes" : {  } , "measures" : { "Sessions" : 57 , "PageViews" : 57 , "SinglePageViewSessions" : 32 , "EntryPageSessions" : 57 , "AvgViewTimeSec" : 91.7272727272727 , "BounceRate" : 56.140350877193 , "ViewsperSession" : 1 } , "SubRows" : null }  , "Slider" : {  "attributes" : {  } , "measures" : { "Sessions" : 57 , "PageViews" : 57 , "SinglePageViewSessions" : 32 , "EntryPageSessions" : 57 , "AvgViewTimeSec" : 91.7272727272727 , "BounceRate" : 56.140350877193 , "ViewsperSession" : 1 } , "SubRows" : null }  , "People I am following" : {  "attributes" : {  } , "measures" : { "Sessions" : 57 , "PageViews" : 57 , "SinglePageViewSessions" : 32 , "EntryPageSessions" : 57 , "AvgViewTimeSec" : 91.7272727272727 , "BounceRate" : 56.140350877193 , "ViewsperSession" : 1 } , "SubRows" : null }  , "Location Navigation" : {  "attributes" : {  } , "measures" : { "Sessions" : 57 , "PageViews" : 57 , "SinglePageViewSessions" : 32 , "EntryPageSessions" : 57 , "AvgViewTimeSec" : 91.7272727272727 , "BounceRate" : 56.140350877193 , "ViewsperSession" : 1 } , "SubRows" : null }  , "Sites I am following" : {  "attributes" : {  } , "measures" : { "Sessions" : 57 , "PageViews" : 57 , "SinglePageViewSessions" : 32 , "EntryPageSessions" : 57 , "AvgViewTimeSec" : 91.7272727272727 , "BounceRate" : 56.140350877193 , "ViewsperSession" : 1 } , "SubRows" : null }  , "Small Input Search Box" : {  "attributes" : {  } , "measures" : { "Sessions" : 57 , "PageViews" : 57 , "SinglePageViewSessions" : 32 , "EntryPageSessions" : 57 , "AvgViewTimeSec" : 91.7272727272727 , "BounceRate" : 56.140350877193 , "ViewsperSession" : 1 } , "SubRows" : null }  , "Yammer" : {  "attributes" : {  } , "measures" : { "Sessions" : 57 , "PageViews" : 57 , "SinglePageViewSessions" : 32 , "EntryPageSessions" : 57 , "AvgViewTimeSec" : 91.7272727272727 , "BounceRate" : 56.140350877193 , "ViewsperSession" : 1 } , "SubRows" : null }  , "Home page script" : {  "attributes" : {  } , "measures" : { "Sessions" : 57 , "PageViews" : 57 , "SinglePageViewSessions" : 32 , "EntryPageSessions" : 57 , "AvgViewTimeSec" : 91.7272727272727 , "BounceRate" : 56.140350877193 , "ViewsperSession" : 1 } , "SubRows" : null }  , "Script Editor" : {  "attributes" : {  } , "measures" : { "Sessions" : 31 , "PageViews" : 31 , "SinglePageViewSessions" : 31 , "EntryPageSessions" : 31 , "AvgViewTimeSec" : null , "BounceRate" : 100 , "ViewsperSession" : 1 } , "SubRows" : null }  , "\u00C9diteur de script" : {  "attributes" : {  } , "measures" : { "Sessions" : 26 , "PageViews" : 26 , "SinglePageViewSessions" : 1 , "EntryPageSessions" : 26 , "AvgViewTimeSec" : 91.7272727272727 , "BounceRate" : 3.84615384615385 , "ViewsperSession" : 1 } , "SubRows" : null }  } } , "Information Technology" : {  "attributes" : {  } , "measures" : { "Sessions" : 31 , "PageViews" : 122 , "SinglePageViewSessions" : 1 , "EntryPageSessions" : 62 , "AvgViewTimeSec" : null , "BounceRate" : 1.61290322580645 , "ViewsperSession" : 3.93548387096774 } , "SubRows" : { "Small Input Search Box" : {  "attributes" : {  } , "measures" : { "Sessions" : 31 , "PageViews" : 61 , "SinglePageViewSessions" : 1 , "EntryPageSessions" : 31 , "AvgViewTimeSec" : null , "BounceRate" : 3.2258064516129 , "ViewsperSession" : 1.96774193548387 } , "SubRows" : null }  , "Todays News" : {  "attributes" : {  } , "measures" : { "Sessions" : 31 , "PageViews" : 61 , "SinglePageViewSessions" : 1 , "EntryPageSessions" : 31 , "AvgViewTimeSec" : null , "BounceRate" : 3.2258064516129 , "ViewsperSession" : 1.96774193548387 } , "SubRows" : null }  , "SupplyChain" : {  "attributes" : {  } , "measures" : { "Sessions" : 31 , "PageViews" : 0 , "SinglePageViewSessions" : 1 , "EntryPageSessions" : 0 , "AvgViewTimeSec" : null , "BounceRate" : null , "ViewsperSession" : 0 } , "SubRows" : null }  } } , "InsideFocus" : {  "attributes" : {  } , "measures" : { "Sessions" : 93 , "PageViews" : 2787 , "SinglePageViewSessions" : 0 , "EntryPageSessions" : 334 , "AvgViewTimeSec" : 104.88764940239 , "BounceRate" : 0 , "ViewsperSession" : 29.9677419354839 } , "SubRows" : { "Content Query" : {  "attributes" : {  } , "measures" : { "Sessions" : 93 , "PageViews" : 215 , "SinglePageViewSessions" : 0 , "EntryPageSessions" : 30 , "AvgViewTimeSec" : 54.3860465116279 , "BounceRate" : 0 , "ViewsperSession" : 2.31182795698925 } , "SubRows" : null }  , "Choose Subsite" : {  "attributes" : {  } , "measures" : { "Sessions" : 93 , "PageViews" : 215 , "SinglePageViewSessions" : 0 , "EntryPageSessions" : 30 , "AvgViewTimeSec" : 54.3860465116279 , "BounceRate" : 0 , "ViewsperSession" : 2.31182795698925 } , "SubRows" : null }  , "Images" : {  "attributes" : {  } , "measures" : { "Sessions" : 93 , "PageViews" : 215 , "SinglePageViewSessions" : 0 , "EntryPageSessions" : 30 , "AvgViewTimeSec" : 54.3860465116279 , "BounceRate" : 0 , "ViewsperSession" : 2.31182795698925 } , "SubRows" : null }  , "Search SearchBox" : {  "attributes" : {  } , "measures" : { "Sessions" : 93 , "PageViews" : 336 , "SinglePageViewSessions" : 0 , "EntryPageSessions" : 31 , "AvgViewTimeSec" : 172.567346938776 , "BounceRate" : 0 , "ViewsperSession" : 3.61290322580645 } , "SubRows" : null }  , "Small Input Search Box" : {  "attributes" : {  } , "measures" : { "Sessions" : 93 , "PageViews" : 215 , "SinglePageViewSessions" : 0 , "EntryPageSessions" : 30 , "AvgViewTimeSec" : 54.3860465116279 , "BounceRate" : 0 , "ViewsperSession" : 2.31182795698925 } , "SubRows" : null }  , "Custom List" : {  "attributes" : {  } , "measures" : { "Sessions" : 93 , "PageViews" : 215 , "SinglePageViewSessions" : 0 , "EntryPageSessions" : 30 , "AvgViewTimeSec" : 54.3860465116279 , "BounceRate" : 0 , "ViewsperSession" : 2.31182795698925 } , "SubRows" : null }  , "Script Editor" : {  "attributes" : {  } , "measures" : { "Sessions" : 93 , "PageViews" : 215 , "SinglePageViewSessions" : 0 , "EntryPageSessions" : 30 , "AvgViewTimeSec" : 54.3860465116279 , "BounceRate" : 0 , "ViewsperSession" : 2.31182795698925 } , "SubRows" : null }  , "Documents" : {  "attributes" : {  } , "measures" : { "Sessions" : 93 , "PageViews" : 246 , "SinglePageViewSessions" : 0 , "EntryPageSessions" : 30 , "AvgViewTimeSec" : 118.487804878049 , "BounceRate" : 0 , "ViewsperSession" : 2.64516129032258 } , "SubRows" : null }  , "Search Refinement" : {  "attributes" : {  } , "measures" : { "Sessions" : 62 , "PageViews" : 305 , "SinglePageViewSessions" : 0 , "EntryPageSessions" : 31 , "AvgViewTimeSec" : 166.917695473251 , "BounceRate" : 0 , "ViewsperSession" : 4.91935483870968 } , "SubRows" : null }  , "Search DataProvider" : {  "attributes" : {  } , "measures" : { "Sessions" : 62 , "PageViews" : 305 , "SinglePageViewSessions" : 0 , "EntryPageSessions" : 31 , "AvgViewTimeSec" : 166.917695473251 , "BounceRate" : 0 , "ViewsperSession" : 4.91935483870968 } , "SubRows" : null }  , "Search Result" : {  "attributes" : {  } , "measures" : { "Sessions" : 62 , "PageViews" : 305 , "SinglePageViewSessions" : 0 , "EntryPageSessions" : 31 , "AvgViewTimeSec" : 166.917695473251 , "BounceRate" : 0 , "ViewsperSession" : 4.91935483870968 } , "SubRows" : null }  } } , "InsideFocusGroup" : {  "attributes" : {  } , "measures" : { "Sessions" : 31 , "PageViews" : 217 , "SinglePageViewSessions" : 0 , "EntryPageSessions" : 0 , "AvgViewTimeSec" : 10 , "BounceRate" : null , "ViewsperSession" : 7 } , "SubRows" : { "Document library" : {  "attributes" : {  } , "measures" : { "Sessions" : 31 , "PageViews" : 31 , "SinglePageViewSessions" : 0 , "EntryPageSessions" : 0 , "AvgViewTimeSec" : 10 , "BounceRate" : null , "ViewsperSession" : 1 } , "SubRows" : null }  , "News" : {  "attributes" : {  } , "measures" : { "Sessions" : 31 , "PageViews" : 31 , "SinglePageViewSessions" : 0 , "EntryPageSessions" : 0 , "AvgViewTimeSec" : 10 , "BounceRate" : null , "ViewsperSession" : 1 } , "SubRows" : null }  , "Site activity" : {  "attributes" : {  } , "measures" : { "Sessions" : 31 , "PageViews" : 31 , "SinglePageViewSessions" : 0 , "EntryPageSessions" : 0 , "AvgViewTimeSec" : 10 , "BounceRate" : null , "ViewsperSession" : 1 } , "SubRows" : null }  , "Quick links" : {  "attributes" : {  } , "measures" : { "Sessions" : 31 , "PageViews" : 31 , "SinglePageViewSessions" : 0 , "EntryPageSessions" : 0 , "AvgViewTimeSec" : 10 , "BounceRate" : null , "ViewsperSession" : 1 } , "SubRows" : null }  , "Hero" : {  "attributes" : {  } , "measures" : { "Sessions" : 31 , "PageViews" : 62 , "SinglePageViewSessions" : 0 , "EntryPageSessions" : 0 , "AvgViewTimeSec" : 10 , "BounceRate" : null , "ViewsperSession" : 2 } , "SubRows" : null }  , "Lista" : {  "attributes" : {  } , "measures" : { "Sessions" : 31 , "PageViews" : 31 , "SinglePageViewSessions" : 0 , "EntryPageSessions" : 0 , "AvgViewTimeSec" : 10 , "BounceRate" : null , "ViewsperSession" : 1 } , "SubRows" : null }  } } , "Marketing" : {  "attributes" : {  } , "measures" : { "Sessions" : 92 , "PageViews" : 2268 , "SinglePageViewSessions" : 61 , "EntryPageSessions" : 1104 , "AvgViewTimeSec" : 86.7571234735414 , "BounceRate" : 5.52536231884058 , "ViewsperSession" : 24.6521739130435 } , "SubRows" : { "Script Editor" : {  "attributes" : {  } , "measures" : { "Sessions" : 92 , "PageViews" : 153 , "SinglePageViewSessions" : 61 , "EntryPageSessions" : 92 , "AvgViewTimeSec" : 93.7826086956522 , "BounceRate" : 66.304347826087 , "ViewsperSession" : 1.66304347826087 } , "SubRows" : null }  , "iConnect" : {  "attributes" : {  } , "measures" : { "Sessions" : 92 , "PageViews" : 153 , "SinglePageViewSessions" : 61 , "EntryPageSessions" : 92 , "AvgViewTimeSec" : 93.7826086956522 , "BounceRate" : 66.304347826087 , "ViewsperSession" : 1.66304347826087 } , "SubRows" : null }  , "People Search" : {  "attributes" : {  } , "measures" : { "Sessions" : 92 , "PageViews" : 153 , "SinglePageViewSessions" : 61 , "EntryPageSessions" : 92 , "AvgViewTimeSec" : 93.7826086956522 , "BounceRate" : 66.304347826087 , "ViewsperSession" : 1.66304347826087 } , "SubRows" : null }  , "Yammer" : {  "attributes" : {  } , "measures" : { "Sessions" : 92 , "PageViews" : 153 , "SinglePageViewSessions" : 61 , "EntryPageSessions" : 92 , "AvgViewTimeSec" : 93.7826086956522 , "BounceRate" : 66.304347826087 , "ViewsperSession" : 1.66304347826087 } , "SubRows" : null }  , "Small Input Search Box" : {  "attributes" : {  } , "measures" : { "Sessions" : 92 , "PageViews" : 369 , "SinglePageViewSessions" : 61 , "EntryPageSessions" : 92 , "AvgViewTimeSec" : 75.0902527075812 , "BounceRate" : 66.304347826087 , "ViewsperSession" : 4.01086956521739 } , "SubRows" : null }  , "People I am following" : {  "attributes" : {  } , "measures" : { "Sessions" : 92 , "PageViews" : 153 , "SinglePageViewSessions" : 61 , "EntryPageSessions" : 92 , "AvgViewTimeSec" : 93.7826086956522 , "BounceRate" : 66.304347826087 , "ViewsperSession" : 1.66304347826087 } , "SubRows" : null }  , "Home page script" : {  "attributes" : {  } , "measures" : { "Sessions" : 92 , "PageViews" : 153 , "SinglePageViewSessions" : 61 , "EntryPageSessions" : 92 , "AvgViewTimeSec" : 93.7826086956522 , "BounceRate" : 66.304347826087 , "ViewsperSession" : 1.66304347826087 } , "SubRows" : null }  , "Slider" : {  "attributes" : {  } , "measures" : { "Sessions" : 92 , "PageViews" : 153 , "SinglePageViewSessions" : 61 , "EntryPageSessions" : 92 , "AvgViewTimeSec" : 93.7826086956522 , "BounceRate" : 66.304347826087 , "ViewsperSession" : 1.66304347826087 } , "SubRows" : null }  , "Featured Links" : {  "attributes" : {  } , "measures" : { "Sessions" : 92 , "PageViews" : 153 , "SinglePageViewSessions" : 61 , "EntryPageSessions" : 92 , "AvgViewTimeSec" : 93.7826086956522 , "BounceRate" : 66.304347826087 , "ViewsperSession" : 1.66304347826087 } , "SubRows" : null }  , "Sites I am following" : {  "attributes" : {  } , "measures" : { "Sessions" : 92 , "PageViews" : 153 , "SinglePageViewSessions" : 61 , "EntryPageSessions" : 92 , "AvgViewTimeSec" : 93.7826086956522 , "BounceRate" : 66.304347826087 , "ViewsperSession" : 1.66304347826087 } , "SubRows" : null }  , "Location Navigation" : {  "attributes" : {  } , "measures" : { "Sessions" : 92 , "PageViews" : 153 , "SinglePageViewSessions" : 61 , "EntryPageSessions" : 92 , "AvgViewTimeSec" : 93.7826086956522 , "BounceRate" : 66.304347826087 , "ViewsperSession" : 1.66304347826087 } , "SubRows" : null }  , "Stock" : {  "attributes" : {  } , "measures" : { "Sessions" : 92 , "PageViews" : 153 , "SinglePageViewSessions" : 61 , "EntryPageSessions" : 92 , "AvgViewTimeSec" : 93.7826086956522 , "BounceRate" : 66.304347826087 , "ViewsperSession" : 1.66304347826087 } , "SubRows" : null }  , "Calendar" : {  "attributes" : {  } , "measures" : { "Sessions" : 31 , "PageViews" : 93 , "SinglePageViewSessions" : 0 , "EntryPageSessions" : 0 , "AvgViewTimeSec" : 26.741935483871 , "BounceRate" : null , "ViewsperSession" : 3 } , "SubRows" : null }  , "CEONews" : {  "attributes" : {  } , "measures" : { "Sessions" : 31 , "PageViews" : 123 , "SinglePageViewSessions" : 0 , "EntryPageSessions" : 0 , "AvgViewTimeSec" : 85.479674796748 , "BounceRate" : null , "ViewsperSession" : 3.96774193548387 } , "SubRows" : null }  } } , "Marketing & Communications" : {  "attributes" : {  } , "measures" : { "Sessions" : 30 , "PageViews" : 120 , "SinglePageViewSessions" : 0 , "EntryPageSessions" : 0 , "AvgViewTimeSec" : 73 , "BounceRate" : null , "ViewsperSession" : 4 } , "SubRows" : { "CQWP - Dashboard items" : {  "attributes" : {  } , "measures" : { "Sessions" : 30 , "PageViews" : 30 , "SinglePageViewSessions" : 0 , "EntryPageSessions" : 0 , "AvgViewTimeSec" : 73 , "BounceRate" : null , "ViewsperSession" : 1 } , "SubRows" : null }  , "CQWP - dashboard headers" : {  "attributes" : {  } , "measures" : { "Sessions" : 30 , "PageViews" : 30 , "SinglePageViewSessions" : 0 , "EntryPageSessions" : 0 , "AvgViewTimeSec" : 73 , "BounceRate" : null , "ViewsperSession" : 1 } , "SubRows" : null }  , "Small Input Search Box" : {  "attributes" : {  } , "measures" : { "Sessions" : 30 , "PageViews" : 30 , "SinglePageViewSessions" : 0 , "EntryPageSessions" : 0 , "AvgViewTimeSec" : 73 , "BounceRate" : null , "ViewsperSession" : 1 } , "SubRows" : null }  , "HTML - dashboard contents" : {  "attributes" : {  } , "measures" : { "Sessions" : 30 , "PageViews" : 30 , "SinglePageViewSessions" : 0 , "EntryPageSessions" : 0 , "AvgViewTimeSec" : 73 , "BounceRate" : null , "ViewsperSession" : 1 } , "SubRows" : null }  } } , "mywebtrends" : {  "attributes" : {  } , "measures" : { "Sessions" : 104 , "PageViews" : 2208 , "SinglePageViewSessions" : 24 , "EntryPageSessions" : 1248 , "AvgViewTimeSec" : 352.873873873874 , "BounceRate" : 1.92307692307692 , "ViewsperSession" : 21.2307692307692 } , "SubRows" : { "Sites I am following" : {  "attributes" : {  } , "measures" : { "Sessions" : 104 , "PageViews" : 184 , "SinglePageViewSessions" : 24 , "EntryPageSessions" : 104 , "AvgViewTimeSec" : 352.873873873874 , "BounceRate" : 23.0769230769231 , "ViewsperSession" : 1.76923076923077 } , "SubRows" : null }  , "People I am following" : {  "attributes" : {  } , "measures" : { "Sessions" : 104 , "PageViews" : 184 , "SinglePageViewSessions" : 24 , "EntryPageSessions" : 104 , "AvgViewTimeSec" : 352.873873873874 , "BounceRate" : 23.0769230769231 , "ViewsperSession" : 1.76923076923077 } , "SubRows" : null }  , "Slider" : {  "attributes" : {  } , "measures" : { "Sessions" : 104 , "PageViews" : 184 , "SinglePageViewSessions" : 24 , "EntryPageSessions" : 104 , "AvgViewTimeSec" : 352.873873873874 , "BounceRate" : 23.0769230769231 , "ViewsperSession" : 1.76923076923077 } , "SubRows" : null }  , "Small Input Search Box" : {  "attributes" : {  } , "measures" : { "Sessions" : 104 , "PageViews" : 184 , "SinglePageViewSessions" : 24 , "EntryPageSessions" : 104 , "AvgViewTimeSec" : 352.873873873874 , "BounceRate" : 23.0769230769231 , "ViewsperSession" : 1.76923076923077 } , "SubRows" : null }  , "Stock" : {  "attributes" : {  } , "measures" : { "Sessions" : 104 , "PageViews" : 184 , "SinglePageViewSessions" : 24 , "EntryPageSessions" : 104 , "AvgViewTimeSec" : 352.873873873874 , "BounceRate" : 23.0769230769231 , "ViewsperSession" : 1.76923076923077 } , "SubRows" : null }  , "Home page script" : {  "attributes" : {  } , "measures" : { "Sessions" : 104 , "PageViews" : 184 , "SinglePageViewSessions" : 24 , "EntryPageSessions" : 104 , "AvgViewTimeSec" : 352.873873873874 , "BounceRate" : 23.0769230769231 , "ViewsperSession" : 1.76923076923077 } , "SubRows" : null }  , "Script Editor" : {  "attributes" : {  } , "measures" : { "Sessions" : 104 , "PageViews" : 184 , "SinglePageViewSessions" : 24 , "EntryPageSessions" : 104 , "AvgViewTimeSec" : 352.873873873874 , "BounceRate" : 23.0769230769231 , "ViewsperSession" : 1.76923076923077 } , "SubRows" : null }  , "Featured Links" : {  "attributes" : {  } , "measures" : { "Sessions" : 104 , "PageViews" : 184 , "SinglePageViewSessions" : 24 , "EntryPageSessions" : 104 , "AvgViewTimeSec" : 352.873873873874 , "BounceRate" : 23.0769230769231 , "ViewsperSession" : 1.76923076923077 } , "SubRows" : null }  , "People Search" : {  "attributes" : {  } , "measures" : { "Sessions" : 104 , "PageViews" : 184 , "SinglePageViewSessions" : 24 , "EntryPageSessions" : 104 , "AvgViewTimeSec" : 352.873873873874 , "BounceRate" : 23.0769230769231 , "ViewsperSession" : 1.76923076923077 } , "SubRows" : null }  , "Yammer" : {  "attributes" : {  } , "measures" : { "Sessions" : 104 , "PageViews" : 184 , "SinglePageViewSessions" : 24 , "EntryPageSessions" : 104 , "AvgViewTimeSec" : 352.873873873874 , "BounceRate" : 23.0769230769231 , "ViewsperSession" : 1.76923076923077 } , "SubRows" : null }  , "Location Navigation" : {  "attributes" : {  } , "measures" : { "Sessions" : 104 , "PageViews" : 184 , "SinglePageViewSessions" : 24 , "EntryPageSessions" : 104 , "AvgViewTimeSec" : 352.873873873874 , "BounceRate" : 23.0769230769231 , "ViewsperSession" : 1.76923076923077 } , "SubRows" : null }  , "iConnect" : {  "attributes" : {  } , "measures" : { "Sessions" : 104 , "PageViews" : 184 , "SinglePageViewSessions" : 24 , "EntryPageSessions" : 104 , "AvgViewTimeSec" : 352.873873873874 , "BounceRate" : 23.0769230769231 , "ViewsperSession" : 1.76923076923077 } , "SubRows" : null }  } } , "No collection name provided" : {  "attributes" : {  } , "measures" : { "Sessions" : 62 , "PageViews" : 671 , "SinglePageViewSessions" : 0 , "EntryPageSessions" : 0 , "AvgViewTimeSec" : 218.490721649485 , "BounceRate" : null , "ViewsperSession" : 10.8225806451613 } , "SubRows" : { "Search Navigation" : {  "attributes" : {  } , "measures" : { "Sessions" : 62 , "PageViews" : 122 , "SinglePageViewSessions" : 0 , "EntryPageSessions" : 0 , "AvgViewTimeSec" : 227.208791208791 , "BounceRate" : null , "ViewsperSession" : 1.96774193548387 } , "SubRows" : null }  , "Search Results" : {  "attributes" : {  } , "measures" : { "Sessions" : 62 , "PageViews" : 122 , "SinglePageViewSessions" : 0 , "EntryPageSessions" : 0 , "AvgViewTimeSec" : 227.208791208791 , "BounceRate" : null , "ViewsperSession" : 1.96774193548387 } , "SubRows" : null }  , "Refinement" : {  "attributes" : {  } , "measures" : { "Sessions" : 62 , "PageViews" : 122 , "SinglePageViewSessions" : 0 , "EntryPageSessions" : 0 , "AvgViewTimeSec" : 227.208791208791 , "BounceRate" : null , "ViewsperSession" : 1.96774193548387 } , "SubRows" : null }  , "Search Box" : {  "attributes" : {  } , "measures" : { "Sessions" : 62 , "PageViews" : 122 , "SinglePageViewSessions" : 0 , "EntryPageSessions" : 0 , "AvgViewTimeSec" : 227.208791208791 , "BounceRate" : null , "ViewsperSession" : 1.96774193548387 } , "SubRows" : null }  , "Small Input Search Box" : {  "attributes" : {  } , "measures" : { "Sessions" : 62 , "PageViews" : 183 , "SinglePageViewSessions" : 0 , "EntryPageSessions" : 0 , "AvgViewTimeSec" : 192.264462809917 , "BounceRate" : null , "ViewsperSession" : 2.95161290322581 } , "SubRows" : null }  } } , "ProductDevelopment" : {  "attributes" : {  } , "measures" : { "Sessions" : 62 , "PageViews" : 1464 , "SinglePageViewSessions" : 1 , "EntryPageSessions" : 624 , "AvgViewTimeSec" : 269.71875 , "BounceRate" : 0.16025641025641 , "ViewsperSession" : 23.6129032258065 } , "SubRows" : { "Sites I am following" : {  "attributes" : {  } , "measures" : { "Sessions" : 62 , "PageViews" : 122 , "SinglePageViewSessions" : 1 , "EntryPageSessions" : 52 , "AvgViewTimeSec" : 269.71875 , "BounceRate" : 1.92307692307692 , "ViewsperSession" : 1.96774193548387 } , "SubRows" : null }  , "Slider" : {  "attributes" : {  } , "measures" : { "Sessions" : 62 , "PageViews" : 122 , "SinglePageViewSessions" : 1 , "EntryPageSessions" : 52 , "AvgViewTimeSec" : 269.71875 , "BounceRate" : 1.92307692307692 , "ViewsperSession" : 1.96774193548387 } , "SubRows" : null }  , "Location Navigation" : {  "attributes" : {  } , "measures" : { "Sessions" : 62 , "PageViews" : 122 , "SinglePageViewSessions" : 1 , "EntryPageSessions" : 52 , "AvgViewTimeSec" : 269.71875 , "BounceRate" : 1.92307692307692 , "ViewsperSession" : 1.96774193548387 } , "SubRows" : null }  , "People Search" : {  "attributes" : {  } , "measures" : { "Sessions" : 62 , "PageViews" : 122 , "SinglePageViewSessions" : 1 , "EntryPageSessions" : 52 , "AvgViewTimeSec" : 269.71875 , "BounceRate" : 1.92307692307692 , "ViewsperSession" : 1.96774193548387 } , "SubRows" : null }  , "iConnect" : {  "attributes" : {  } , "measures" : { "Sessions" : 62 , "PageViews" : 122 , "SinglePageViewSessions" : 1 , "EntryPageSessions" : 52 , "AvgViewTimeSec" : 269.71875 , "BounceRate" : 1.92307692307692 , "ViewsperSession" : 1.96774193548387 } , "SubRows" : null }  , "Script Editor" : {  "attributes" : {  } , "measures" : { "Sessions" : 62 , "PageViews" : 122 , "SinglePageViewSessions" : 1 , "EntryPageSessions" : 52 , "AvgViewTimeSec" : 269.71875 , "BounceRate" : 1.92307692307692 , "ViewsperSession" : 1.96774193548387 } , "SubRows" : null }  , "People I am following" : {  "attributes" : {  } , "measures" : { "Sessions" : 62 , "PageViews" : 122 , "SinglePageViewSessions" : 1 , "EntryPageSessions" : 52 , "AvgViewTimeSec" : 269.71875 , "BounceRate" : 1.92307692307692 , "ViewsperSession" : 1.96774193548387 } , "SubRows" : null }  , "Small Input Search Box" : {  "attributes" : {  } , "measures" : { "Sessions" : 62 , "PageViews" : 122 , "SinglePageViewSessions" : 1 , "EntryPageSessions" : 52 , "AvgViewTimeSec" : 269.71875 , "BounceRate" : 1.92307692307692 , "ViewsperSession" : 1.96774193548387 } , "SubRows" : null }  , "Home page script" : {  "attributes" : {  } , "measures" : { "Sessions" : 62 , "PageViews" : 122 , "SinglePageViewSessions" : 1 , "EntryPageSessions" : 52 , "AvgViewTimeSec" : 269.71875 , "BounceRate" : 1.92307692307692 , "ViewsperSession" : 1.96774193548387 } , "SubRows" : null }  , "Featured Links" : {  "attributes" : {  } , "measures" : { "Sessions" : 62 , "PageViews" : 122 , "SinglePageViewSessions" : 1 , "EntryPageSessions" : 52 , "AvgViewTimeSec" : 269.71875 , "BounceRate" : 1.92307692307692 , "ViewsperSession" : 1.96774193548387 } , "SubRows" : null }  , "Yammer" : {  "attributes" : {  } , "measures" : { "Sessions" : 62 , "PageViews" : 122 , "SinglePageViewSessions" : 1 , "EntryPageSessions" : 52 , "AvgViewTimeSec" : 269.71875 , "BounceRate" : 1.92307692307692 , "ViewsperSession" : 1.96774193548387 } , "SubRows" : null }  , "Stock" : {  "attributes" : {  } , "measures" : { "Sessions" : 62 , "PageViews" : 122 , "SinglePageViewSessions" : 1 , "EntryPageSessions" : 52 , "AvgViewTimeSec" : 269.71875 , "BounceRate" : 1.92307692307692 , "ViewsperSession" : 1.96774193548387 } , "SubRows" : null }  } } , "Spanish" : {  "attributes" : {  } , "measures" : { "Sessions" : 63 , "PageViews" : 541 , "SinglePageViewSessions" : 0 , "EntryPageSessions" : 191 , "AvgViewTimeSec" : 331.648780487805 , "BounceRate" : 0 , "ViewsperSession" : 8.58730158730159 } , "SubRows" : { "Lista Personalizada" : {  "attributes" : {  } , "measures" : { "Sessions" : 32 , "PageViews" : 96 , "SinglePageViewSessions" : 0 , "EntryPageSessions" : 32 , "AvgViewTimeSec" : 386.528571428571 , "BounceRate" : 0 , "ViewsperSession" : 3 } , "SubRows" : null }  , "Documentos" : {  "attributes" : {  } , "measures" : { "Sessions" : 32 , "PageViews" : 96 , "SinglePageViewSessions" : 0 , "EntryPageSessions" : 32 , "AvgViewTimeSec" : 386.528571428571 , "BounceRate" : 0 , "ViewsperSession" : 3 } , "SubRows" : null }  , "Iniciando su sitio" : {  "attributes" : {  } , "measures" : { "Sessions" : 32 , "PageViews" : 96 , "SinglePageViewSessions" : 0 , "EntryPageSessions" : 32 , "AvgViewTimeSec" : 386.528571428571 , "BounceRate" : 0 , "ViewsperSession" : 3 } , "SubRows" : null }  , "RSS de sitio" : {  "attributes" : {  } , "measures" : { "Sessions" : 32 , "PageViews" : 96 , "SinglePageViewSessions" : 0 , "EntryPageSessions" : 32 , "AvgViewTimeSec" : 386.528571428571 , "BounceRate" : 0 , "ViewsperSession" : 3 } , "SubRows" : null }  , "Small Input Search Box" : {  "attributes" : {  } , "measures" : { "Sessions" : 32 , "PageViews" : 96 , "SinglePageViewSessions" : 0 , "EntryPageSessions" : 32 , "AvgViewTimeSec" : 386.528571428571 , "BounceRate" : 0 , "ViewsperSession" : 3 } , "SubRows" : null }  , "Search SearchBox" : {  "attributes" : {  } , "measures" : { "Sessions" : 31 , "PageViews" : 61 , "SinglePageViewSessions" : 0 , "EntryPageSessions" : 31 , "AvgViewTimeSec" : 11.5166666666667 , "BounceRate" : 0 , "ViewsperSession" : 1.96774193548387 } , "SubRows" : null }  } } , "SpanishNews" : {  "attributes" : {  } , "measures" : { "Sessions" : 62 , "PageViews" : 500 , "SinglePageViewSessions" : 0 , "EntryPageSessions" : 0 , "AvgViewTimeSec" : 166.078125 , "BounceRate" : null , "ViewsperSession" : 8.06451612903226 } , "SubRows" : { "News" : {  "attributes" : {  } , "measures" : { "Sessions" : 62 , "PageViews" : 125 , "SinglePageViewSessions" : 0 , "EntryPageSessions" : 0 , "AvgViewTimeSec" : 166.078125 , "BounceRate" : null , "ViewsperSession" : 2.01612903225806 } , "SubRows" : null }  , "Site activity" : {  "attributes" : {  } , "measures" : { "Sessions" : 62 , "PageViews" : 125 , "SinglePageViewSessions" : 0 , "EntryPageSessions" : 0 , "AvgViewTimeSec" : 166.078125 , "BounceRate" : null , "ViewsperSession" : 2.01612903225806 } , "SubRows" : null }  , "Document library" : {  "attributes" : {  } , "measures" : { "Sessions" : 62 , "PageViews" : 125 , "SinglePageViewSessions" : 0 , "EntryPageSessions" : 0 , "AvgViewTimeSec" : 166.078125 , "BounceRate" : null , "ViewsperSession" : 2.01612903225806 } , "SubRows" : null }  , "Quick links" : {  "attributes" : {  } , "measures" : { "Sessions" : 62 , "PageViews" : 125 , "SinglePageViewSessions" : 0 , "EntryPageSessions" : 0 , "AvgViewTimeSec" : 166.078125 , "BounceRate" : null , "ViewsperSession" : 2.01612903225806 } , "SubRows" : null }  } } , "Strategy" : {  "attributes" : {  } , "measures" : { "Sessions" : 31 , "PageViews" : 1116 , "SinglePageViewSessions" : 0 , "EntryPageSessions" : 372 , "AvgViewTimeSec" : 78 , "BounceRate" : 0 , "ViewsperSession" : 36 } , "SubRows" : { "Sites I am following" : {  "attributes" : {  } , "measures" : { "Sessions" : 31 , "PageViews" : 93 , "SinglePageViewSessions" : 0 , "EntryPageSessions" : 31 , "AvgViewTimeSec" : 78 , "BounceRate" : 0 , "ViewsperSession" : 3 } , "SubRows" : null }  , "Yammer" : {  "attributes" : {  } , "measures" : { "Sessions" : 31 , "PageViews" : 93 , "SinglePageViewSessions" : 0 , "EntryPageSessions" : 31 , "AvgViewTimeSec" : 78 , "BounceRate" : 0 , "ViewsperSession" : 3 } , "SubRows" : null }  , "Featured Links" : {  "attributes" : {  } , "measures" : { "Sessions" : 31 , "PageViews" : 93 , "SinglePageViewSessions" : 0 , "EntryPageSessions" : 31 , "AvgViewTimeSec" : 78 , "BounceRate" : 0 , "ViewsperSession" : 3 } , "SubRows" : null }  , "Home page script" : {  "attributes" : {  } , "measures" : { "Sessions" : 31 , "PageViews" : 93 , "SinglePageViewSessions" : 0 , "EntryPageSessions" : 31 , "AvgViewTimeSec" : 78 , "BounceRate" : 0 , "ViewsperSession" : 3 } , "SubRows" : null }  , "Small Input Search Box" : {  "attributes" : {  } , "measures" : { "Sessions" : 31 , "PageViews" : 93 , "SinglePageViewSessions" : 0 , "EntryPageSessions" : 31 , "AvgViewTimeSec" : 78 , "BounceRate" : 0 , "ViewsperSession" : 3 } , "SubRows" : null }  , "Location Navigation" : {  "attributes" : {  } , "measures" : { "Sessions" : 31 , "PageViews" : 93 , "SinglePageViewSessions" : 0 , "EntryPageSessions" : 31 , "AvgViewTimeSec" : 78 , "BounceRate" : 0 , "ViewsperSession" : 3 } , "SubRows" : null }  , "iConnect" : {  "attributes" : {  } , "measures" : { "Sessions" : 31 , "PageViews" : 93 , "SinglePageViewSessions" : 0 , "EntryPageSessions" : 31 , "AvgViewTimeSec" : 78 , "BounceRate" : 0 , "ViewsperSession" : 3 } , "SubRows" : null }  , "People Search" : {  "attributes" : {  } , "measures" : { "Sessions" : 31 , "PageViews" : 93 , "SinglePageViewSessions" : 0 , "EntryPageSessions" : 31 , "AvgViewTimeSec" : 78 , "BounceRate" : 0 , "ViewsperSession" : 3 } , "SubRows" : null }  , "Script Editor" : {  "attributes" : {  } , "measures" : { "Sessions" : 31 , "PageViews" : 93 , "SinglePageViewSessions" : 0 , "EntryPageSessions" : 31 , "AvgViewTimeSec" : 78 , "BounceRate" : 0 , "ViewsperSession" : 3 } , "SubRows" : null }  , "People I am following" : {  "attributes" : {  } , "measures" : { "Sessions" : 31 , "PageViews" : 93 , "SinglePageViewSessions" : 0 , "EntryPageSessions" : 31 , "AvgViewTimeSec" : 78 , "BounceRate" : 0 , "ViewsperSession" : 3 } , "SubRows" : null }  , "Stock" : {  "attributes" : {  } , "measures" : { "Sessions" : 31 , "PageViews" : 93 , "SinglePageViewSessions" : 0 , "EntryPageSessions" : 31 , "AvgViewTimeSec" : 78 , "BounceRate" : 0 , "ViewsperSession" : 3 } , "SubRows" : null }  , "Slider" : {  "attributes" : {  } , "measures" : { "Sessions" : 31 , "PageViews" : 93 , "SinglePageViewSessions" : 0 , "EntryPageSessions" : 31 , "AvgViewTimeSec" : 78 , "BounceRate" : 0 , "ViewsperSession" : 3 } , "SubRows" : null }  } } } ] } ] }