{ "definition" : { "accountID" : 24252 , "profileID" : "zzDVIQJKL88" , "ID" : "qNPokGtbKb8" , "name" : "User Login: User Drilldown" , "description" : "This report provides details into your SharePoint users." , "language" : null , "timezone" : "UTC 1" , "dimensions" : [ { "ID" : "z1XNbNMJFh7" , "name" : "User Login" },{ "ID" : "hF0vfdiWgB8" , "name" : "SP: User Location" },{ "ID" : "DiSSZHTzp27" , "name" : "SharePoint Office" },{ "ID" : "R79RONNkFh7" , "name" : "SP 2013: User Department" },{ "ID" : "pCNSApQkFh7" , "name" : "SP 2013: User Job Title" } ] , "measures" : [ { "name" : "Sessions" , "ID" : "Visits" , "columnID" : 0 , "measureFormatType" : null },{ "name" : "PageViews" , "ID" : "CAoNYspmFb5" , "columnID" : 1 , "measureFormatType" : null },{ "name" : "SinglePageViewSessions" , "ID" : "JP3fwtZ7DM6" , "columnID" : 3 , "measureFormatType" : null },{ "name" : "EntryPageSessions" , "ID" : "RDqgRX18DM6" , "columnID" : 4 , "measureFormatType" : null },{ "name" : "AvgViewTimeSec" , "ID" : "fC51LCSmFb5" , "columnID" : 5 , "measureFormatType" : null },{ "name" : "DocumentInteractions" , "ID" : "spH5fTBpFh7" , "columnID" : 6 , "measureFormatType" : null },{ "name" : "SocialInteractions" , "ID" : "ksUnaQDpFh7" , "columnID" : 7 , "measureFormatType" : null },{ "name" : "ListInteractions" , "ID" : "2UHt4JFpFh7" , "columnID" : 8 , "measureFormatType" : null },{ "name" : "AvgSessionDurationMins" , "ID" : "9VUp0ikQJb5" , "columnID" : 10 , "measureFormatType" : null },{ "name" : "BounceRate" , "ID" : "HzywuEAkVM6" , "columnID" : 2 , "measureFormatType" : "percent" },{ "name" : "ViewsperSession" , "ID" : "HtIZlKwbKb8" , "columnID" : 9 , "measureFormatType" : "numeric" } ] } ,"data" : [ { "period" : "Day" , "start_date" : "2021-10-01" , "end_date" : "2021-10-31" , "attributes" : {  } , "measures" : { "Sessions" : 1063 , "PageViews" : 3244 , "SinglePageViewSessions" : 243 , "EntryPageSessions" : 842 , "DocumentInteractions" : 332 , "SocialInteractions" : 1672 , "ListInteractions" : 123 , "AvgViewTimeSec" : 145.897727272727 , "AvgSessionDurationMins" : 6.32060201975541 , "BounceRate" : 28.8598574821853 , "ViewsperSession" : 3.05174035747883 } , "SubRows" : [  { "aperez@webtrends.com" : {  "attributes" : {  } , "measures" : { "Sessions" : 73 , "PageViews" : 61 , "SinglePageViewSessions" : 23 , "EntryPageSessions" : 42 , "DocumentInteractions" : 0 , "SocialInteractions" : 0 , "ListInteractions" : 0 , "AvgViewTimeSec" : 1775 , "AvgSessionDurationMins" : 7.69977165753425 , "BounceRate" : 54.7619047619048 , "ViewsperSession" : 0.835616438356164 } , "SubRows" : { "Spain_East" : {  "attributes" : {  } , "measures" : { "Sessions" : 73 , "PageViews" : 61 , "SinglePageViewSessions" : 23 , "EntryPageSessions" : 42 , "DocumentInteractions" : 0 , "SocialInteractions" : 0 , "ListInteractions" : 0 , "AvgViewTimeSec" : 1775 , "AvgSessionDurationMins" : 7.69977165753425 , "BounceRate" : 54.7619047619048 , "ViewsperSession" : 0.835616438356164 } , "SubRows" : { "ES - Barcelona" : {  "attributes" : {  } , "measures" : { "Sessions" : 73 , "PageViews" : 61 , "SinglePageViewSessions" : 23 , "EntryPageSessions" : 42 , "DocumentInteractions" : 0 , "SocialInteractions" : 0 , "ListInteractions" : 0 , "AvgViewTimeSec" : 1775 , "AvgSessionDurationMins" : 7.69977165753425 , "BounceRate" : 54.7619047619048 , "ViewsperSession" : 0.835616438356164 } , "SubRows" : { "Sales" : {  "attributes" : {  } , "measures" : { "Sessions" : 73 , "PageViews" : 61 , "SinglePageViewSessions" : 23 , "EntryPageSessions" : 42 , "DocumentInteractions" : 0 , "SocialInteractions" : 0 , "ListInteractions" : 0 , "AvgViewTimeSec" : 1775 , "AvgSessionDurationMins" : 7.69977165753425 , "BounceRate" : 54.7619047619048 , "ViewsperSession" : 0.835616438356164 } , "SubRows" : { "Sales Manager" : {  "attributes" : {  } , "measures" : { "Sessions" : 73 , "PageViews" : 61 , "SinglePageViewSessions" : 23 , "EntryPageSessions" : 42 , "DocumentInteractions" : 0 , "SocialInteractions" : 0 , "ListInteractions" : 0 , "AvgViewTimeSec" : 1775 , "AvgSessionDurationMins" : 7.69977165753425 , "BounceRate" : 54.7619047619048 , "ViewsperSession" : 0.835616438356164 } , "SubRows" : null }  } } } } } } } } , "bchillwell@webtrends.com" : {  "attributes" : {  } , "measures" : { "Sessions" : 62 , "PageViews" : 400 , "SinglePageViewSessions" : 1 , "EntryPageSessions" : 62 , "DocumentInteractions" : 28 , "SocialInteractions" : 0 , "ListInteractions" : 0 , "AvgViewTimeSec" : 43.801775147929 , "AvgSessionDurationMins" : 3.97983872580645 , "BounceRate" : 1.61290322580645 , "ViewsperSession" : 6.45161290322581 } , "SubRows" : { "No location provided" : {  "attributes" : {  } , "measures" : { "Sessions" : 62 , "PageViews" : 400 , "SinglePageViewSessions" : 1 , "EntryPageSessions" : 62 , "DocumentInteractions" : 28 , "SocialInteractions" : 0 , "ListInteractions" : 0 , "AvgViewTimeSec" : 43.801775147929 , "AvgSessionDurationMins" : 3.97983872580645 , "BounceRate" : 1.61290322580645 , "ViewsperSession" : 6.45161290322581 } , "SubRows" : { "NC - Raleigh" : {  "attributes" : {  } , "measures" : { "Sessions" : 62 , "PageViews" : 400 , "SinglePageViewSessions" : 1 , "EntryPageSessions" : 62 , "DocumentInteractions" : 28 , "SocialInteractions" : 0 , "ListInteractions" : 0 , "AvgViewTimeSec" : 43.801775147929 , "AvgSessionDurationMins" : 3.97983872580645 , "BounceRate" : 1.61290322580645 , "ViewsperSession" : 6.45161290322581 } , "SubRows" : { "Learning & Documentation" : {  "attributes" : {  } , "measures" : { "Sessions" : 62 , "PageViews" : 400 , "SinglePageViewSessions" : 1 , "EntryPageSessions" : 62 , "DocumentInteractions" : 28 , "SocialInteractions" : 0 , "ListInteractions" : 0 , "AvgViewTimeSec" : 43.801775147929 , "AvgSessionDurationMins" : 3.97983872580645 , "BounceRate" : 1.61290322580645 , "ViewsperSession" : 6.45161290322581 } , "SubRows" : { "Sr Technical Writer" : {  "attributes" : {  } , "measures" : { "Sessions" : 62 , "PageViews" : 400 , "SinglePageViewSessions" : 1 , "EntryPageSessions" : 62 , "DocumentInteractions" : 28 , "SocialInteractions" : 0 , "ListInteractions" : 0 , "AvgViewTimeSec" : 43.801775147929 , "AvgSessionDurationMins" : 3.97983872580645 , "BounceRate" : 1.61290322580645 , "ViewsperSession" : 6.45161290322581 } , "SubRows" : null }  } } } } } } } } , "cfuchs@webtrends.com" : {  "attributes" : {  } , "measures" : { "Sessions" : 62 , "PageViews" : 31 , "SinglePageViewSessions" : 31 , "EntryPageSessions" : 31 , "DocumentInteractions" : 0 , "SocialInteractions" : 0 , "ListInteractions" : 0 , "AvgViewTimeSec" : null , "AvgSessionDurationMins" : 0 , "BounceRate" : 100 , "ViewsperSession" : 0.5 } , "SubRows" : { "No location provided" : {  "attributes" : {  } , "measures" : { "Sessions" : 62 , "PageViews" : 31 , "SinglePageViewSessions" : 31 , "EntryPageSessions" : 31 , "DocumentInteractions" : 0 , "SocialInteractions" : 0 , "ListInteractions" : 0 , "AvgViewTimeSec" : null , "AvgSessionDurationMins" : 0 , "BounceRate" : 100 , "ViewsperSession" : 0.5 } , "SubRows" : { "DE - Karlsruhe" : {  "attributes" : {  } , "measures" : { "Sessions" : 62 , "PageViews" : 31 , "SinglePageViewSessions" : 31 , "EntryPageSessions" : 31 , "DocumentInteractions" : 0 , "SocialInteractions" : 0 , "ListInteractions" : 0 , "AvgViewTimeSec" : null , "AvgSessionDurationMins" : 0 , "BounceRate" : 100 , "ViewsperSession" : 0.5 } , "SubRows" : { "Devices-EMEA/APAC Gas Devices" : {  "attributes" : {  } , "measures" : { "Sessions" : 62 , "PageViews" : 31 , "SinglePageViewSessions" : 31 , "EntryPageSessions" : 31 , "DocumentInteractions" : 0 , "SocialInteractions" : 0 , "ListInteractions" : 0 , "AvgViewTimeSec" : null , "AvgSessionDurationMins" : 0 , "BounceRate" : 100 , "ViewsperSession" : 0.5 } , "SubRows" : { "Design Engineer" : {  "attributes" : {  } , "measures" : { "Sessions" : 62 , "PageViews" : 31 , "SinglePageViewSessions" : 31 , "EntryPageSessions" : 31 , "DocumentInteractions" : 0 , "SocialInteractions" : 0 , "ListInteractions" : 0 , "AvgViewTimeSec" : null , "AvgSessionDurationMins" : 0 , "BounceRate" : 100 , "ViewsperSession" : 0.5 } , "SubRows" : null }  } } } } } } } } , "fbenkovic@webtrends.com" : {  "attributes" : {  } , "measures" : { "Sessions" : 123 , "PageViews" : 183 , "SinglePageViewSessions" : 31 , "EntryPageSessions" : 92 , "DocumentInteractions" : 0 , "SocialInteractions" : 122 , "ListInteractions" : 0 , "AvgViewTimeSec" : 20.765625 , "AvgSessionDurationMins" : 0.615176032520325 , "BounceRate" : 33.695652173913 , "ViewsperSession" : 1.48780487804878 } , "SubRows" : { "No location provided" : {  "attributes" : {  } , "measures" : { "Sessions" : 123 , "PageViews" : 183 , "SinglePageViewSessions" : 31 , "EntryPageSessions" : 92 , "DocumentInteractions" : 0 , "SocialInteractions" : 122 , "ListInteractions" : 0 , "AvgViewTimeSec" : 20.765625 , "AvgSessionDurationMins" : 0.615176032520325 , "BounceRate" : 33.695652173913 , "ViewsperSession" : 1.48780487804878 } , "SubRows" : { "BUD - Budapest" : {  "attributes" : {  } , "measures" : { "Sessions" : 123 , "PageViews" : 183 , "SinglePageViewSessions" : 31 , "EntryPageSessions" : 92 , "DocumentInteractions" : 0 , "SocialInteractions" : 122 , "ListInteractions" : 0 , "AvgViewTimeSec" : 20.765625 , "AvgSessionDurationMins" : 0.615176032520325 , "BounceRate" : 33.695652173913 , "ViewsperSession" : 1.48780487804878 } , "SubRows" : { "Budapest COE" : {  "attributes" : {  } , "measures" : { "Sessions" : 123 , "PageViews" : 183 , "SinglePageViewSessions" : 31 , "EntryPageSessions" : 92 , "DocumentInteractions" : 0 , "SocialInteractions" : 122 , "ListInteractions" : 0 , "AvgViewTimeSec" : 20.765625 , "AvgSessionDurationMins" : 0.615176032520325 , "BounceRate" : 33.695652173913 , "ViewsperSession" : 1.48780487804878 } , "SubRows" : { "Software Engineer" : {  "attributes" : {  } , "measures" : { "Sessions" : 123 , "PageViews" : 183 , "SinglePageViewSessions" : 31 , "EntryPageSessions" : 92 , "DocumentInteractions" : 0 , "SocialInteractions" : 122 , "ListInteractions" : 0 , "AvgViewTimeSec" : 20.765625 , "AvgSessionDurationMins" : 0.615176032520325 , "BounceRate" : 33.695652173913 , "ViewsperSession" : 1.48780487804878 } , "SubRows" : null }  } } } } } } } } , "glineker@webtrends.com" : {  "attributes" : {  } , "measures" : { "Sessions" : 31 , "PageViews" : 212 , "SinglePageViewSessions" : 0 , "EntryPageSessions" : 31 , "DocumentInteractions" : 29 , "SocialInteractions" : 273 , "ListInteractions" : 0 , "AvgViewTimeSec" : 402.977653631285 , "AvgSessionDurationMins" : 38.8521505483871 , "BounceRate" : 0 , "ViewsperSession" : 6.83870967741935 } , "SubRows" : { "No location provided" : {  "attributes" : {  } , "measures" : { "Sessions" : 31 , "PageViews" : 212 , "SinglePageViewSessions" : 0 , "EntryPageSessions" : 31 , "DocumentInteractions" : 29 , "SocialInteractions" : 273 , "ListInteractions" : 0 , "AvgViewTimeSec" : 402.977653631285 , "AvgSessionDurationMins" : 38.8521505483871 , "BounceRate" : 0 , "ViewsperSession" : 6.83870967741935 } , "SubRows" : { "West Coast" : {  "attributes" : {  } , "measures" : { "Sessions" : 31 , "PageViews" : 212 , "SinglePageViewSessions" : 0 , "EntryPageSessions" : 31 , "DocumentInteractions" : 29 , "SocialInteractions" : 273 , "ListInteractions" : 0 , "AvgViewTimeSec" : 402.977653631285 , "AvgSessionDurationMins" : 38.8521505483871 , "BounceRate" : 0 , "ViewsperSession" : 6.83870967741935 } , "SubRows" : { "Engineering" : {  "attributes" : {  } , "measures" : { "Sessions" : 31 , "PageViews" : 212 , "SinglePageViewSessions" : 0 , "EntryPageSessions" : 31 , "DocumentInteractions" : 29 , "SocialInteractions" : 273 , "ListInteractions" : 0 , "AvgViewTimeSec" : 402.977653631285 , "AvgSessionDurationMins" : 38.8521505483871 , "BounceRate" : 0 , "ViewsperSession" : 6.83870967741935 } , "SubRows" : { "Research Manager" : {  "attributes" : {  } , "measures" : { "Sessions" : 31 , "PageViews" : 212 , "SinglePageViewSessions" : 0 , "EntryPageSessions" : 31 , "DocumentInteractions" : 29 , "SocialInteractions" : 273 , "ListInteractions" : 0 , "AvgViewTimeSec" : 402.977653631285 , "AvgSessionDurationMins" : 38.8521505483871 , "BounceRate" : 0 , "ViewsperSession" : 6.83870967741935 } , "SubRows" : null }  } } } } } } } } , "hbarnes@webtrends.com" : {  "attributes" : {  } , "measures" : { "Sessions" : 62 , "PageViews" : 214 , "SinglePageViewSessions" : 1 , "EntryPageSessions" : 62 , "DocumentInteractions" : 0 , "SocialInteractions" : 92 , "ListInteractions" : 0 , "AvgViewTimeSec" : 151.669291338583 , "AvgSessionDurationMins" : 5.23064509677419 , "BounceRate" : 1.61290322580645 , "ViewsperSession" : 3.45161290322581 } , "SubRows" : { "No location provided" : {  "attributes" : {  } , "measures" : { "Sessions" : 62 , "PageViews" : 214 , "SinglePageViewSessions" : 1 , "EntryPageSessions" : 62 , "DocumentInteractions" : 0 , "SocialInteractions" : 92 , "ListInteractions" : 0 , "AvgViewTimeSec" : 151.669291338583 , "AvgSessionDurationMins" : 5.23064509677419 , "BounceRate" : 1.61290322580645 , "ViewsperSession" : 3.45161290322581 } , "SubRows" : { "IE - CO Cork" : {  "attributes" : {  } , "measures" : { "Sessions" : 62 , "PageViews" : 214 , "SinglePageViewSessions" : 1 , "EntryPageSessions" : 62 , "DocumentInteractions" : 0 , "SocialInteractions" : 92 , "ListInteractions" : 0 , "AvgViewTimeSec" : 151.669291338583 , "AvgSessionDurationMins" : 5.23064509677419 , "BounceRate" : 1.61290322580645 , "ViewsperSession" : 3.45161290322581 } , "SubRows" : { "Global Business Services" : {  "attributes" : {  } , "measures" : { "Sessions" : 62 , "PageViews" : 214 , "SinglePageViewSessions" : 1 , "EntryPageSessions" : 62 , "DocumentInteractions" : 0 , "SocialInteractions" : 92 , "ListInteractions" : 0 , "AvgViewTimeSec" : 151.669291338583 , "AvgSessionDurationMins" : 5.23064509677419 , "BounceRate" : 1.61290322580645 , "ViewsperSession" : 3.45161290322581 } , "SubRows" : { "Sr Accounting Clerk" : {  "attributes" : {  } , "measures" : { "Sessions" : 62 , "PageViews" : 214 , "SinglePageViewSessions" : 1 , "EntryPageSessions" : 62 , "DocumentInteractions" : 0 , "SocialInteractions" : 92 , "ListInteractions" : 0 , "AvgViewTimeSec" : 151.669291338583 , "AvgSessionDurationMins" : 5.23064509677419 , "BounceRate" : 1.61290322580645 , "ViewsperSession" : 3.45161290322581 } , "SubRows" : null }  } } } } } } } } , "hchoudhury@webtrends.com" : {  "attributes" : {  } , "measures" : { "Sessions" : 32 , "PageViews" : 0 , "SinglePageViewSessions" : 0 , "EntryPageSessions" : 0 , "DocumentInteractions" : 0 , "SocialInteractions" : 0 , "ListInteractions" : 0 , "AvgViewTimeSec" : null , "AvgSessionDurationMins" : 0 , "BounceRate" : null , "ViewsperSession" : 0 } , "SubRows" : { "No location provided" : {  "attributes" : {  } , "measures" : { "Sessions" : 32 , "PageViews" : 0 , "SinglePageViewSessions" : 0 , "EntryPageSessions" : 0 , "DocumentInteractions" : 0 , "SocialInteractions" : 0 , "ListInteractions" : 0 , "AvgViewTimeSec" : null , "AvgSessionDurationMins" : 0 , "BounceRate" : null , "ViewsperSession" : 0 } , "SubRows" : { "FR - Meudon" : {  "attributes" : {  } , "measures" : { "Sessions" : 32 , "PageViews" : 0 , "SinglePageViewSessions" : 0 , "EntryPageSessions" : 0 , "DocumentInteractions" : 0 , "SocialInteractions" : 0 , "ListInteractions" : 0 , "AvgViewTimeSec" : null , "AvgSessionDurationMins" : 0 , "BounceRate" : null , "ViewsperSession" : 0 } , "SubRows" : { "CTO-Hardware" : {  "attributes" : {  } , "measures" : { "Sessions" : 32 , "PageViews" : 0 , "SinglePageViewSessions" : 0 , "EntryPageSessions" : 0 , "DocumentInteractions" : 0 , "SocialInteractions" : 0 , "ListInteractions" : 0 , "AvgViewTimeSec" : null , "AvgSessionDurationMins" : 0 , "BounceRate" : null , "ViewsperSession" : 0 } , "SubRows" : { "Principal Research Engineer" : {  "attributes" : {  } , "measures" : { "Sessions" : 32 , "PageViews" : 0 , "SinglePageViewSessions" : 0 , "EntryPageSessions" : 0 , "DocumentInteractions" : 0 , "SocialInteractions" : 0 , "ListInteractions" : 0 , "AvgViewTimeSec" : null , "AvgSessionDurationMins" : 0 , "BounceRate" : null , "ViewsperSession" : 0 } , "SubRows" : null }  } } } } } } } } , "hgondorf@webtrends.com" : {  "attributes" : {  } , "measures" : { "Sessions" : 31 , "PageViews" : 521 , "SinglePageViewSessions" : 0 , "EntryPageSessions" : 31 , "DocumentInteractions" : 124 , "SocialInteractions" : 0 , "ListInteractions" : 0 , "AvgViewTimeSec" : 135.142857142857 , "AvgSessionDurationMins" : 35.6021502580645 , "BounceRate" : 0 , "ViewsperSession" : 16.8064516129032 } , "SubRows" : { "No location provided" : {  "attributes" : {  } , "measures" : { "Sessions" : 31 , "PageViews" : 521 , "SinglePageViewSessions" : 0 , "EntryPageSessions" : 31 , "DocumentInteractions" : 124 , "SocialInteractions" : 0 , "ListInteractions" : 0 , "AvgViewTimeSec" : 135.142857142857 , "AvgSessionDurationMins" : 35.6021502580645 , "BounceRate" : 0 , "ViewsperSession" : 16.8064516129032 } , "SubRows" : { "Western Region" : {  "attributes" : {  } , "measures" : { "Sessions" : 31 , "PageViews" : 521 , "SinglePageViewSessions" : 0 , "EntryPageSessions" : 31 , "DocumentInteractions" : 124 , "SocialInteractions" : 0 , "ListInteractions" : 0 , "AvgViewTimeSec" : 135.142857142857 , "AvgSessionDurationMins" : 35.6021502580645 , "BounceRate" : 0 , "ViewsperSession" : 16.8064516129032 } , "SubRows" : { "Client Services" : {  "attributes" : {  } , "measures" : { "Sessions" : 31 , "PageViews" : 521 , "SinglePageViewSessions" : 0 , "EntryPageSessions" : 31 , "DocumentInteractions" : 124 , "SocialInteractions" : 0 , "ListInteractions" : 0 , "AvgViewTimeSec" : 135.142857142857 , "AvgSessionDurationMins" : 35.6021502580645 , "BounceRate" : 0 , "ViewsperSession" : 16.8064516129032 } , "SubRows" : { "VP Client Services" : {  "attributes" : {  } , "measures" : { "Sessions" : 31 , "PageViews" : 521 , "SinglePageViewSessions" : 0 , "EntryPageSessions" : 31 , "DocumentInteractions" : 124 , "SocialInteractions" : 0 , "ListInteractions" : 0 , "AvgViewTimeSec" : 135.142857142857 , "AvgSessionDurationMins" : 35.6021502580645 , "BounceRate" : 0 , "ViewsperSession" : 16.8064516129032 } , "SubRows" : null }  } } } } } } } } , "jevans@webtrends.com" : {  "attributes" : {  } , "measures" : { "Sessions" : 31 , "PageViews" : 31 , "SinglePageViewSessions" : 31 , "EntryPageSessions" : 31 , "DocumentInteractions" : 0 , "SocialInteractions" : 0 , "ListInteractions" : 0 , "AvgViewTimeSec" : null , "AvgSessionDurationMins" : 0 , "BounceRate" : 100 , "ViewsperSession" : 1 } , "SubRows" : { "No location provided" : {  "attributes" : {  } , "measures" : { "Sessions" : 31 , "PageViews" : 31 , "SinglePageViewSessions" : 31 , "EntryPageSessions" : 31 , "DocumentInteractions" : 0 , "SocialInteractions" : 0 , "ListInteractions" : 0 , "AvgViewTimeSec" : null , "AvgSessionDurationMins" : 0 , "BounceRate" : 100 , "ViewsperSession" : 1 } , "SubRows" : { "GB - Felixstowe" : {  "attributes" : {  } , "measures" : { "Sessions" : 31 , "PageViews" : 31 , "SinglePageViewSessions" : 31 , "EntryPageSessions" : 31 , "DocumentInteractions" : 0 , "SocialInteractions" : 0 , "ListInteractions" : 0 , "AvgViewTimeSec" : null , "AvgSessionDurationMins" : 0 , "BounceRate" : 100 , "ViewsperSession" : 1 } , "SubRows" : { "Software & Service Dev Ops Exe" : {  "attributes" : {  } , "measures" : { "Sessions" : 31 , "PageViews" : 31 , "SinglePageViewSessions" : 31 , "EntryPageSessions" : 31 , "DocumentInteractions" : 0 , "SocialInteractions" : 0 , "ListInteractions" : 0 , "AvgViewTimeSec" : null , "AvgSessionDurationMins" : 0 , "BounceRate" : 100 , "ViewsperSession" : 1 } , "SubRows" : { "Sr Project Manager" : {  "attributes" : {  } , "measures" : { "Sessions" : 31 , "PageViews" : 31 , "SinglePageViewSessions" : 31 , "EntryPageSessions" : 31 , "DocumentInteractions" : 0 , "SocialInteractions" : 0 , "ListInteractions" : 0 , "AvgViewTimeSec" : null , "AvgSessionDurationMins" : 0 , "BounceRate" : 100 , "ViewsperSession" : 1 } , "SubRows" : null }  } } } } } } } } , "jhooker@webtrends.com" : {  "attributes" : {  } , "measures" : { "Sessions" : 32 , "PageViews" : 254 , "SinglePageViewSessions" : 0 , "EntryPageSessions" : 32 , "DocumentInteractions" : 0 , "SocialInteractions" : 941 , "ListInteractions" : 0 , "AvgViewTimeSec" : 239.29696969697 , "AvgSessionDurationMins" : 43.55 , "BounceRate" : 0 , "ViewsperSession" : 7.9375 } , "SubRows" : { "No location provided" : {  "attributes" : {  } , "measures" : { "Sessions" : 32 , "PageViews" : 254 , "SinglePageViewSessions" : 0 , "EntryPageSessions" : 32 , "DocumentInteractions" : 0 , "SocialInteractions" : 941 , "ListInteractions" : 0 , "AvgViewTimeSec" : 239.29696969697 , "AvgSessionDurationMins" : 43.55 , "BounceRate" : 0 , "ViewsperSession" : 7.9375 } , "SubRows" : { "Cascade Region" : {  "attributes" : {  } , "measures" : { "Sessions" : 32 , "PageViews" : 254 , "SinglePageViewSessions" : 0 , "EntryPageSessions" : 32 , "DocumentInteractions" : 0 , "SocialInteractions" : 941 , "ListInteractions" : 0 , "AvgViewTimeSec" : 239.29696969697 , "AvgSessionDurationMins" : 43.55 , "BounceRate" : 0 , "ViewsperSession" : 7.9375 } , "SubRows" : { "Engineering" : {  "attributes" : {  } , "measures" : { "Sessions" : 32 , "PageViews" : 254 , "SinglePageViewSessions" : 0 , "EntryPageSessions" : 32 , "DocumentInteractions" : 0 , "SocialInteractions" : 941 , "ListInteractions" : 0 , "AvgViewTimeSec" : 239.29696969697 , "AvgSessionDurationMins" : 43.55 , "BounceRate" : 0 , "ViewsperSession" : 7.9375 } , "SubRows" : { "Sr Engineer" : {  "attributes" : {  } , "measures" : { "Sessions" : 32 , "PageViews" : 254 , "SinglePageViewSessions" : 0 , "EntryPageSessions" : 32 , "DocumentInteractions" : 0 , "SocialInteractions" : 941 , "ListInteractions" : 0 , "AvgViewTimeSec" : 239.29696969697 , "AvgSessionDurationMins" : 43.55 , "BounceRate" : 0 , "ViewsperSession" : 7.9375 } , "SubRows" : null }  } } } } } } } } , "jmower@webtrends.com" : {  "attributes" : {  } , "measures" : { "Sessions" : 31 , "PageViews" : 62 , "SinglePageViewSessions" : 0 , "EntryPageSessions" : 31 , "DocumentInteractions" : 0 , "SocialInteractions" : 62 , "ListInteractions" : 0 , "AvgViewTimeSec" : 14 , "AvgSessionDurationMins" : 0.233333032258065 , "BounceRate" : 0 , "ViewsperSession" : 2 } , "SubRows" : { "No location provided" : {  "attributes" : {  } , "measures" : { "Sessions" : 31 , "PageViews" : 62 , "SinglePageViewSessions" : 0 , "EntryPageSessions" : 31 , "DocumentInteractions" : 0 , "SocialInteractions" : 62 , "ListInteractions" : 0 , "AvgViewTimeSec" : 14 , "AvgSessionDurationMins" : 0.233333032258065 , "BounceRate" : 0 , "ViewsperSession" : 2 } , "SubRows" : { "Prineville" : {  "attributes" : {  } , "measures" : { "Sessions" : 31 , "PageViews" : 62 , "SinglePageViewSessions" : 0 , "EntryPageSessions" : 31 , "DocumentInteractions" : 0 , "SocialInteractions" : 62 , "ListInteractions" : 0 , "AvgViewTimeSec" : 14 , "AvgSessionDurationMins" : 0.233333032258065 , "BounceRate" : 0 , "ViewsperSession" : 2 } , "SubRows" : { "John Day Services" : {  "attributes" : {  } , "measures" : { "Sessions" : 31 , "PageViews" : 62 , "SinglePageViewSessions" : 0 , "EntryPageSessions" : 31 , "DocumentInteractions" : 0 , "SocialInteractions" : 62 , "ListInteractions" : 0 , "AvgViewTimeSec" : 14 , "AvgSessionDurationMins" : 0.233333032258065 , "BounceRate" : 0 , "ViewsperSession" : 2 } , "SubRows" : { "Sr Planner" : {  "attributes" : {  } , "measures" : { "Sessions" : 31 , "PageViews" : 62 , "SinglePageViewSessions" : 0 , "EntryPageSessions" : 31 , "DocumentInteractions" : 0 , "SocialInteractions" : 62 , "ListInteractions" : 0 , "AvgViewTimeSec" : 14 , "AvgSessionDurationMins" : 0.233333032258065 , "BounceRate" : 0 , "ViewsperSession" : 2 } , "SubRows" : null }  } } } } } } } } , "kcameron@webtrends.com" : {  "attributes" : {  } , "measures" : { "Sessions" : 63 , "PageViews" : 93 , "SinglePageViewSessions" : 0 , "EntryPageSessions" : 31 , "DocumentInteractions" : 0 , "SocialInteractions" : 0 , "ListInteractions" : 0 , "AvgViewTimeSec" : 78 , "AvgSessionDurationMins" : 1.27936507936508 , "BounceRate" : 0 , "ViewsperSession" : 1.47619047619048 } , "SubRows" : { "No location provided" : {  "attributes" : {  } , "measures" : { "Sessions" : 63 , "PageViews" : 93 , "SinglePageViewSessions" : 0 , "EntryPageSessions" : 31 , "DocumentInteractions" : 0 , "SocialInteractions" : 0 , "ListInteractions" : 0 , "AvgViewTimeSec" : 78 , "AvgSessionDurationMins" : 1.27936507936508 , "BounceRate" : 0 , "ViewsperSession" : 1.47619047619048 } , "SubRows" : { "NC - Raleigh" : {  "attributes" : {  } , "measures" : { "Sessions" : 63 , "PageViews" : 93 , "SinglePageViewSessions" : 0 , "EntryPageSessions" : 31 , "DocumentInteractions" : 0 , "SocialInteractions" : 0 , "ListInteractions" : 0 , "AvgViewTimeSec" : 78 , "AvgSessionDurationMins" : 1.27936507936508 , "BounceRate" : 0 , "ViewsperSession" : 1.47619047619048 } , "SubRows" : { "Hardware Development" : {  "attributes" : {  } , "measures" : { "Sessions" : 32 , "PageViews" : 0 , "SinglePageViewSessions" : 0 , "EntryPageSessions" : 0 , "DocumentInteractions" : 0 , "SocialInteractions" : 0 , "ListInteractions" : 0 , "AvgViewTimeSec" : null , "AvgSessionDurationMins" : 0 , "BounceRate" : null , "ViewsperSession" : 0 } , "SubRows" : { "Software Engineer" : {  "attributes" : {  } , "measures" : { "Sessions" : 32 , "PageViews" : 0 , "SinglePageViewSessions" : 0 , "EntryPageSessions" : 0 , "DocumentInteractions" : 0 , "SocialInteractions" : 0 , "ListInteractions" : 0 , "AvgViewTimeSec" : null , "AvgSessionDurationMins" : 0 , "BounceRate" : null , "ViewsperSession" : 0 } , "SubRows" : null }  } } , "Firmware-Mains Powered" : {  "attributes" : {  } , "measures" : { "Sessions" : 31 , "PageViews" : 93 , "SinglePageViewSessions" : 0 , "EntryPageSessions" : 31 , "DocumentInteractions" : 0 , "SocialInteractions" : 0 , "ListInteractions" : 0 , "AvgViewTimeSec" : 78 , "AvgSessionDurationMins" : 2.6 , "BounceRate" : 0 , "ViewsperSession" : 3 } , "SubRows" : { "Software Engineer" : {  "attributes" : {  } , "measures" : { "Sessions" : 31 , "PageViews" : 93 , "SinglePageViewSessions" : 0 , "EntryPageSessions" : 31 , "DocumentInteractions" : 0 , "SocialInteractions" : 0 , "ListInteractions" : 0 , "AvgViewTimeSec" : 78 , "AvgSessionDurationMins" : 2.6 , "BounceRate" : 0 , "ViewsperSession" : 3 } , "SubRows" : null }  } } } } } } } } , "kreynolds@webtrends.com" : {  "attributes" : {  } , "measures" : { "Sessions" : 31 , "PageViews" : 62 , "SinglePageViewSessions" : 0 , "EntryPageSessions" : 31 , "DocumentInteractions" : 30 , "SocialInteractions" : 0 , "ListInteractions" : 0 , "AvgViewTimeSec" : 50.1290322580645 , "AvgSessionDurationMins" : 0.835483580645161 , "BounceRate" : 0 , "ViewsperSession" : 2 } , "SubRows" : { "No location provided" : {  "attributes" : {  } , "measures" : { "Sessions" : 31 , "PageViews" : 62 , "SinglePageViewSessions" : 0 , "EntryPageSessions" : 31 , "DocumentInteractions" : 30 , "SocialInteractions" : 0 , "ListInteractions" : 0 , "AvgViewTimeSec" : 50.1290322580645 , "AvgSessionDurationMins" : 0.835483580645161 , "BounceRate" : 0 , "ViewsperSession" : 2 } , "SubRows" : { "Western Region" : {  "attributes" : {  } , "measures" : { "Sessions" : 31 , "PageViews" : 62 , "SinglePageViewSessions" : 0 , "EntryPageSessions" : 31 , "DocumentInteractions" : 30 , "SocialInteractions" : 0 , "ListInteractions" : 0 , "AvgViewTimeSec" : 50.1290322580645 , "AvgSessionDurationMins" : 0.835483580645161 , "BounceRate" : 0 , "ViewsperSession" : 2 } , "SubRows" : { "Global Business Services" : {  "attributes" : {  } , "measures" : { "Sessions" : 31 , "PageViews" : 62 , "SinglePageViewSessions" : 0 , "EntryPageSessions" : 31 , "DocumentInteractions" : 30 , "SocialInteractions" : 0 , "ListInteractions" : 0 , "AvgViewTimeSec" : 50.1290322580645 , "AvgSessionDurationMins" : 0.835483580645161 , "BounceRate" : 0 , "ViewsperSession" : 2 } , "SubRows" : { "Partner in Charge" : {  "attributes" : {  } , "measures" : { "Sessions" : 31 , "PageViews" : 62 , "SinglePageViewSessions" : 0 , "EntryPageSessions" : 31 , "DocumentInteractions" : 30 , "SocialInteractions" : 0 , "ListInteractions" : 0 , "AvgViewTimeSec" : 50.1290322580645 , "AvgSessionDurationMins" : 0.835483580645161 , "BounceRate" : 0 , "ViewsperSession" : 2 } , "SubRows" : null }  } } } } } } } } , "lcoleman@webtrends.com" : {  "attributes" : {  } , "measures" : { "Sessions" : 31 , "PageViews" : 212 , "SinglePageViewSessions" : 0 , "EntryPageSessions" : 31 , "DocumentInteractions" : 90 , "SocialInteractions" : 0 , "ListInteractions" : 0 , "AvgViewTimeSec" : 212.220994475138 , "AvgSessionDurationMins" : 20.6516126129032 , "BounceRate" : 0 , "ViewsperSession" : 6.83870967741935 } , "SubRows" : { "No location provided" : {  "attributes" : {  } , "measures" : { "Sessions" : 31 , "PageViews" : 212 , "SinglePageViewSessions" : 0 , "EntryPageSessions" : 31 , "DocumentInteractions" : 90 , "SocialInteractions" : 0 , "ListInteractions" : 0 , "AvgViewTimeSec" : 212.220994475138 , "AvgSessionDurationMins" : 20.6516126129032 , "BounceRate" : 0 , "ViewsperSession" : 6.83870967741935 } , "SubRows" : { "Western Region" : {  "attributes" : {  } , "measures" : { "Sessions" : 31 , "PageViews" : 212 , "SinglePageViewSessions" : 0 , "EntryPageSessions" : 31 , "DocumentInteractions" : 90 , "SocialInteractions" : 0 , "ListInteractions" : 0 , "AvgViewTimeSec" : 212.220994475138 , "AvgSessionDurationMins" : 20.6516126129032 , "BounceRate" : 0 , "ViewsperSession" : 6.83870967741935 } , "SubRows" : { "Client Services" : {  "attributes" : {  } , "measures" : { "Sessions" : 31 , "PageViews" : 212 , "SinglePageViewSessions" : 0 , "EntryPageSessions" : 31 , "DocumentInteractions" : 90 , "SocialInteractions" : 0 , "ListInteractions" : 0 , "AvgViewTimeSec" : 212.220994475138 , "AvgSessionDurationMins" : 20.6516126129032 , "BounceRate" : 0 , "ViewsperSession" : 6.83870967741935 } , "SubRows" : { "VP Client Services" : {  "attributes" : {  } , "measures" : { "Sessions" : 31 , "PageViews" : 212 , "SinglePageViewSessions" : 0 , "EntryPageSessions" : 31 , "DocumentInteractions" : 90 , "SocialInteractions" : 0 , "ListInteractions" : 0 , "AvgViewTimeSec" : 212.220994475138 , "AvgSessionDurationMins" : 20.6516126129032 , "BounceRate" : 0 , "ViewsperSession" : 6.83870967741935 } , "SubRows" : null }  } } } } } } } } , "lsalino@webtrends.com" : {  "attributes" : {  } , "measures" : { "Sessions" : 31 , "PageViews" : 182 , "SinglePageViewSessions" : 0 , "EntryPageSessions" : 31 , "DocumentInteractions" : 0 , "SocialInteractions" : 89 , "ListInteractions" : 0 , "AvgViewTimeSec" : 24.3196721311475 , "AvgSessionDurationMins" : 14.9940860322581 , "BounceRate" : 0 , "ViewsperSession" : 5.87096774193548 } , "SubRows" : { "No location provided" : {  "attributes" : {  } , "measures" : { "Sessions" : 61 , "PageViews" : 182 , "SinglePageViewSessions" : 0 , "EntryPageSessions" : 31 , "DocumentInteractions" : 0 , "SocialInteractions" : 89 , "ListInteractions" : 0 , "AvgViewTimeSec" : 24.3196721311475 , "AvgSessionDurationMins" : 14.9939890819672 , "BounceRate" : 0 , "ViewsperSession" : 2.98360655737705 } , "SubRows" : { "Southwest Region" : {  "attributes" : {  } , "measures" : { "Sessions" : 31 , "PageViews" : 182 , "SinglePageViewSessions" : 0 , "EntryPageSessions" : 31 , "DocumentInteractions" : 0 , "SocialInteractions" : 59 , "ListInteractions" : 0 , "AvgViewTimeSec" : 24.3196721311475 , "AvgSessionDurationMins" : 14.9940860322581 , "BounceRate" : 0 , "ViewsperSession" : 5.87096774193548 } , "SubRows" : { "Plant Operations" : {  "attributes" : {  } , "measures" : { "Sessions" : 31 , "PageViews" : 182 , "SinglePageViewSessions" : 0 , "EntryPageSessions" : 31 , "DocumentInteractions" : 0 , "SocialInteractions" : 59 , "ListInteractions" : 0 , "AvgViewTimeSec" : 24.3196721311475 , "AvgSessionDurationMins" : 14.9940860322581 , "BounceRate" : 0 , "ViewsperSession" : 5.87096774193548 } , "SubRows" : { "Plant Manager" : {  "attributes" : {  } , "measures" : { "Sessions" : 31 , "PageViews" : 182 , "SinglePageViewSessions" : 0 , "EntryPageSessions" : 31 , "DocumentInteractions" : 0 , "SocialInteractions" : 59 , "ListInteractions" : 0 , "AvgViewTimeSec" : 24.3196721311475 , "AvgSessionDurationMins" : 14.9940860322581 , "BounceRate" : 0 , "ViewsperSession" : 5.87096774193548 } , "SubRows" : null }  } } } } , "Cascade Region" : {  "attributes" : {  } , "measures" : { "Sessions" : 30 , "PageViews" : 0 , "SinglePageViewSessions" : 0 , "EntryPageSessions" : 0 , "DocumentInteractions" : 0 , "SocialInteractions" : 30 , "ListInteractions" : 0 , "AvgViewTimeSec" : null , "AvgSessionDurationMins" : 14.9938889 , "BounceRate" : null , "ViewsperSession" : 0 } , "SubRows" : { "Engineering" : {  "attributes" : {  } , "measures" : { "Sessions" : 30 , "PageViews" : 0 , "SinglePageViewSessions" : 0 , "EntryPageSessions" : 0 , "DocumentInteractions" : 0 , "SocialInteractions" : 30 , "ListInteractions" : 0 , "AvgViewTimeSec" : null , "AvgSessionDurationMins" : 14.9938889 , "BounceRate" : null , "ViewsperSession" : 0 } , "SubRows" : { "Sr Engineer" : {  "attributes" : {  } , "measures" : { "Sessions" : 30 , "PageViews" : 0 , "SinglePageViewSessions" : 0 , "EntryPageSessions" : 0 , "DocumentInteractions" : 0 , "SocialInteractions" : 30 , "ListInteractions" : 0 , "AvgViewTimeSec" : null , "AvgSessionDurationMins" : 14.9938889 , "BounceRate" : null , "ViewsperSession" : 0 } , "SubRows" : null }  } } } } } } } } , "lsembrant@webtrends.com" : {  "attributes" : {  } , "measures" : { "Sessions" : 31 , "PageViews" : 91 , "SinglePageViewSessions" : 0 , "EntryPageSessions" : 31 , "DocumentInteractions" : 0 , "SocialInteractions" : 0 , "ListInteractions" : 0 , "AvgViewTimeSec" : 12.0338983050847 , "AvgSessionDurationMins" : 0.386559096774194 , "BounceRate" : 0 , "ViewsperSession" : 2.93548387096774 } , "SubRows" : { "No location provided" : {  "attributes" : {  } , "measures" : { "Sessions" : 31 , "PageViews" : 91 , "SinglePageViewSessions" : 0 , "EntryPageSessions" : 31 , "DocumentInteractions" : 0 , "SocialInteractions" : 0 , "ListInteractions" : 0 , "AvgViewTimeSec" : 12.0338983050847 , "AvgSessionDurationMins" : 0.386559096774194 , "BounceRate" : 0 , "ViewsperSession" : 2.93548387096774 } , "SubRows" : { "SE - Stockholm" : {  "attributes" : {  } , "measures" : { "Sessions" : 31 , "PageViews" : 91 , "SinglePageViewSessions" : 0 , "EntryPageSessions" : 31 , "DocumentInteractions" : 0 , "SocialInteractions" : 0 , "ListInteractions" : 0 , "AvgViewTimeSec" : 12.0338983050847 , "AvgSessionDurationMins" : 0.386559096774194 , "BounceRate" : 0 , "ViewsperSession" : 2.93548387096774 } , "SubRows" : { "Technical Support Networks" : {  "attributes" : {  } , "measures" : { "Sessions" : 31 , "PageViews" : 91 , "SinglePageViewSessions" : 0 , "EntryPageSessions" : 31 , "DocumentInteractions" : 0 , "SocialInteractions" : 0 , "ListInteractions" : 0 , "AvgViewTimeSec" : 12.0338983050847 , "AvgSessionDurationMins" : 0.386559096774194 , "BounceRate" : 0 , "ViewsperSession" : 2.93548387096774 } , "SubRows" : { "Technical Suppt Specialist" : {  "attributes" : {  } , "measures" : { "Sessions" : 31 , "PageViews" : 91 , "SinglePageViewSessions" : 0 , "EntryPageSessions" : 31 , "DocumentInteractions" : 0 , "SocialInteractions" : 0 , "ListInteractions" : 0 , "AvgViewTimeSec" : 12.0338983050847 , "AvgSessionDurationMins" : 0.386559096774194 , "BounceRate" : 0 , "ViewsperSession" : 2.93548387096774 } , "SubRows" : null }  } } } } } } } } , "malbrighton@webtrends.com" : {  "attributes" : {  } , "measures" : { "Sessions" : 31 , "PageViews" : 338 , "SinglePageViewSessions" : 0 , "EntryPageSessions" : 31 , "DocumentInteractions" : 0 , "SocialInteractions" : 0 , "ListInteractions" : 123 , "AvgViewTimeSec" : 74.885993485342 , "AvgSessionDurationMins" : 12.3602151935484 , "BounceRate" : 0 , "ViewsperSession" : 10.9032258064516 } , "SubRows" : { "No location provided" : {  "attributes" : {  } , "measures" : { "Sessions" : 31 , "PageViews" : 338 , "SinglePageViewSessions" : 0 , "EntryPageSessions" : 31 , "DocumentInteractions" : 0 , "SocialInteractions" : 0 , "ListInteractions" : 123 , "AvgViewTimeSec" : 74.885993485342 , "AvgSessionDurationMins" : 12.3602151935484 , "BounceRate" : 0 , "ViewsperSession" : 10.9032258064516 } , "SubRows" : { "USA - Remote East" : {  "attributes" : {  } , "measures" : { "Sessions" : 31 , "PageViews" : 338 , "SinglePageViewSessions" : 0 , "EntryPageSessions" : 31 , "DocumentInteractions" : 0 , "SocialInteractions" : 0 , "ListInteractions" : 123 , "AvgViewTimeSec" : 74.885993485342 , "AvgSessionDurationMins" : 12.3602151935484 , "BounceRate" : 0 , "ViewsperSession" : 10.9032258064516 } , "SubRows" : { "Sales" : {  "attributes" : {  } , "measures" : { "Sessions" : 31 , "PageViews" : 338 , "SinglePageViewSessions" : 0 , "EntryPageSessions" : 31 , "DocumentInteractions" : 0 , "SocialInteractions" : 0 , "ListInteractions" : 123 , "AvgViewTimeSec" : 74.885993485342 , "AvgSessionDurationMins" : 12.3602151935484 , "BounceRate" : 0 , "ViewsperSession" : 10.9032258064516 } , "SubRows" : { "Sales Manager" : {  "attributes" : {  } , "measures" : { "Sessions" : 31 , "PageViews" : 338 , "SinglePageViewSessions" : 0 , "EntryPageSessions" : 31 , "DocumentInteractions" : 0 , "SocialInteractions" : 0 , "ListInteractions" : 123 , "AvgViewTimeSec" : 74.885993485342 , "AvgSessionDurationMins" : 12.3602151935484 , "BounceRate" : 0 , "ViewsperSession" : 10.9032258064516 } , "SubRows" : null }  } } } } } } } } , "rbennett@webtrends.com" : {  "attributes" : {  } , "measures" : { "Sessions" : 62 , "PageViews" : 93 , "SinglePageViewSessions" : 31 , "EntryPageSessions" : 62 , "DocumentInteractions" : 0 , "SocialInteractions" : 93 , "ListInteractions" : 0 , "AvgViewTimeSec" : 32 , "AvgSessionDurationMins" : 0.26586014516129 , "BounceRate" : 50 , "ViewsperSession" : 1.5 } , "SubRows" : { "No location provided" : {  "attributes" : {  } , "measures" : { "Sessions" : 62 , "PageViews" : 93 , "SinglePageViewSessions" : 31 , "EntryPageSessions" : 62 , "DocumentInteractions" : 0 , "SocialInteractions" : 93 , "ListInteractions" : 0 , "AvgViewTimeSec" : 32 , "AvgSessionDurationMins" : 0.26586014516129 , "BounceRate" : 50 , "ViewsperSession" : 1.5 } , "SubRows" : { "Clarno" : {  "attributes" : {  } , "measures" : { "Sessions" : 62 , "PageViews" : 93 , "SinglePageViewSessions" : 31 , "EntryPageSessions" : 62 , "DocumentInteractions" : 0 , "SocialInteractions" : 93 , "ListInteractions" : 0 , "AvgViewTimeSec" : 32 , "AvgSessionDurationMins" : 0.26586014516129 , "BounceRate" : 50 , "ViewsperSession" : 1.5 } , "SubRows" : { "Eastern Region" : {  "attributes" : {  } , "measures" : { "Sessions" : 62 , "PageViews" : 93 , "SinglePageViewSessions" : 31 , "EntryPageSessions" : 62 , "DocumentInteractions" : 0 , "SocialInteractions" : 93 , "ListInteractions" : 0 , "AvgViewTimeSec" : 32 , "AvgSessionDurationMins" : 0.26586014516129 , "BounceRate" : 50 , "ViewsperSession" : 1.5 } , "SubRows" : { "Planner" : {  "attributes" : {  } , "measures" : { "Sessions" : 62 , "PageViews" : 93 , "SinglePageViewSessions" : 31 , "EntryPageSessions" : 62 , "DocumentInteractions" : 0 , "SocialInteractions" : 93 , "ListInteractions" : 0 , "AvgViewTimeSec" : 32 , "AvgSessionDurationMins" : 0.26586014516129 , "BounceRate" : 50 , "ViewsperSession" : 1.5 } , "SubRows" : null }  } } } } } } } } , "wmorgan@webtrends.com" : {  "attributes" : {  } , "measures" : { "Sessions" : 93 , "PageViews" : 61 , "SinglePageViewSessions" : 61 , "EntryPageSessions" : 61 , "DocumentInteractions" : 0 , "SocialInteractions" : 0 , "ListInteractions" : 0 , "AvgViewTimeSec" : null , "AvgSessionDurationMins" : 0 , "BounceRate" : 100 , "ViewsperSession" : 0.655913978494624 } , "SubRows" : { "No location provided" : {  "attributes" : {  } , "measures" : { "Sessions" : 93 , "PageViews" : 61 , "SinglePageViewSessions" : 61 , "EntryPageSessions" : 61 , "DocumentInteractions" : 0 , "SocialInteractions" : 0 , "ListInteractions" : 0 , "AvgViewTimeSec" : null , "AvgSessionDurationMins" : 0 , "BounceRate" : 100 , "ViewsperSession" : 0.655913978494624 } , "SubRows" : { "CAN - Ontario Home" : {  "attributes" : {  } , "measures" : { "Sessions" : 93 , "PageViews" : 61 , "SinglePageViewSessions" : 61 , "EntryPageSessions" : 61 , "DocumentInteractions" : 0 , "SocialInteractions" : 0 , "ListInteractions" : 0 , "AvgViewTimeSec" : null , "AvgSessionDurationMins" : 0 , "BounceRate" : 100 , "ViewsperSession" : 0.655913978494624 } , "SubRows" : { "Client Delivery" : {  "attributes" : {  } , "measures" : { "Sessions" : 93 , "PageViews" : 61 , "SinglePageViewSessions" : 61 , "EntryPageSessions" : 61 , "DocumentInteractions" : 0 , "SocialInteractions" : 0 , "ListInteractions" : 0 , "AvgViewTimeSec" : null , "AvgSessionDurationMins" : 0 , "BounceRate" : 100 , "ViewsperSession" : 0.655913978494624 } , "SubRows" : { "Sr Project Manager" : {  "attributes" : {  } , "measures" : { "Sessions" : 93 , "PageViews" : 61 , "SinglePageViewSessions" : 61 , "EntryPageSessions" : 61 , "DocumentInteractions" : 0 , "SocialInteractions" : 0 , "ListInteractions" : 0 , "AvgViewTimeSec" : null , "AvgSessionDurationMins" : 0 , "BounceRate" : 100 , "ViewsperSession" : 0.655913978494624 } , "SubRows" : null }  } } } } } } } } , "wndidi@webtrends.com" : {  "attributes" : {  } , "measures" : { "Sessions" : 26 , "PageViews" : 51 , "SinglePageViewSessions" : 1 , "EntryPageSessions" : 26 , "DocumentInteractions" : 0 , "SocialInteractions" : 0 , "ListInteractions" : 0 , "AvgViewTimeSec" : 91.7272727272727 , "AvgSessionDurationMins" : 1.45512823076923 , "BounceRate" : 3.84615384615385 , "ViewsperSession" : 1.96153846153846 } , "SubRows" : { "No location provided" : {  "attributes" : {  } , "measures" : { "Sessions" : 26 , "PageViews" : 51 , "SinglePageViewSessions" : 1 , "EntryPageSessions" : 26 , "DocumentInteractions" : 0 , "SocialInteractions" : 0 , "ListInteractions" : 0 , "AvgViewTimeSec" : 91.7272727272727 , "AvgSessionDurationMins" : 1.45512823076923 , "BounceRate" : 3.84615384615385 , "ViewsperSession" : 1.96153846153846 } , "SubRows" : { "Macon" : {  "attributes" : {  } , "measures" : { "Sessions" : 26 , "PageViews" : 51 , "SinglePageViewSessions" : 1 , "EntryPageSessions" : 26 , "DocumentInteractions" : 0 , "SocialInteractions" : 0 , "ListInteractions" : 0 , "AvgViewTimeSec" : 91.7272727272727 , "AvgSessionDurationMins" : 1.45512823076923 , "BounceRate" : 3.84615384615385 , "ViewsperSession" : 1.96153846153846 } , "SubRows" : { "Devices-Water Devices" : {  "attributes" : {  } , "measures" : { "Sessions" : 26 , "PageViews" : 51 , "SinglePageViewSessions" : 1 , "EntryPageSessions" : 26 , "DocumentInteractions" : 0 , "SocialInteractions" : 0 , "ListInteractions" : 0 , "AvgViewTimeSec" : 91.7272727272727 , "AvgSessionDurationMins" : 1.45512823076923 , "BounceRate" : 3.84615384615385 , "ViewsperSession" : 1.96153846153846 } , "SubRows" : { "Research Engineer" : {  "attributes" : {  } , "measures" : { "Sessions" : 26 , "PageViews" : 51 , "SinglePageViewSessions" : 1 , "EntryPageSessions" : 26 , "DocumentInteractions" : 0 , "SocialInteractions" : 0 , "ListInteractions" : 0 , "AvgViewTimeSec" : 91.7272727272727 , "AvgSessionDurationMins" : 1.45512823076923 , "BounceRate" : 3.84615384615385 , "ViewsperSession" : 1.96153846153846 } , "SubRows" : null }  } } } } } } } } , "wsiff@webtrends.com" : {  "attributes" : {  } , "measures" : { "Sessions" : 63 , "PageViews" : 31 , "SinglePageViewSessions" : 31 , "EntryPageSessions" : 31 , "DocumentInteractions" : 0 , "SocialInteractions" : 0 , "ListInteractions" : 0 , "AvgViewTimeSec" : null , "AvgSessionDurationMins" : 0 , "BounceRate" : 100 , "ViewsperSession" : 0.492063492063492 } , "SubRows" : { "No location provided" : {  "attributes" : {  } , "measures" : { "Sessions" : 63 , "PageViews" : 31 , "SinglePageViewSessions" : 31 , "EntryPageSessions" : 31 , "DocumentInteractions" : 0 , "SocialInteractions" : 0 , "ListInteractions" : 0 , "AvgViewTimeSec" : null , "AvgSessionDurationMins" : 0 , "BounceRate" : 100 , "ViewsperSession" : 0.492063492063492 } , "SubRows" : { "BUD - Budapest" : {  "attributes" : {  } , "measures" : { "Sessions" : 63 , "PageViews" : 31 , "SinglePageViewSessions" : 31 , "EntryPageSessions" : 31 , "DocumentInteractions" : 0 , "SocialInteractions" : 0 , "ListInteractions" : 0 , "AvgViewTimeSec" : null , "AvgSessionDurationMins" : 0 , "BounceRate" : 100 , "ViewsperSession" : 0.492063492063492 } , "SubRows" : { "MS Technical Operations" : {  "attributes" : {  } , "measures" : { "Sessions" : 63 , "PageViews" : 31 , "SinglePageViewSessions" : 31 , "EntryPageSessions" : 31 , "DocumentInteractions" : 0 , "SocialInteractions" : 0 , "ListInteractions" : 0 , "AvgViewTimeSec" : null , "AvgSessionDurationMins" : 0 , "BounceRate" : 100 , "ViewsperSession" : 0.492063492063492 } , "SubRows" : { "Principal Solutions Architect" : {  "attributes" : {  } , "measures" : { "Sessions" : 63 , "PageViews" : 31 , "SinglePageViewSessions" : 31 , "EntryPageSessions" : 31 , "DocumentInteractions" : 0 , "SocialInteractions" : 0 , "ListInteractions" : 0 , "AvgViewTimeSec" : null , "AvgSessionDurationMins" : 0 , "BounceRate" : 100 , "ViewsperSession" : 0.492063492063492 } , "SubRows" : null }  } } } } } } } } , "ytielemans@webtrends.com" : {  "attributes" : {  } , "measures" : { "Sessions" : 31 , "PageViews" : 61 , "SinglePageViewSessions" : 1 , "EntryPageSessions" : 31 , "DocumentInteractions" : 31 , "SocialInteractions" : 0 , "ListInteractions" : 0 , "AvgViewTimeSec" : null , "AvgSessionDurationMins" : 4.51935493548387 , "BounceRate" : 3.2258064516129 , "ViewsperSession" : 1.96774193548387 } , "SubRows" : { "No location provided" : {  "attributes" : {  } , "measures" : { "Sessions" : 31 , "PageViews" : 61 , "SinglePageViewSessions" : 1 , "EntryPageSessions" : 31 , "DocumentInteractions" : 31 , "SocialInteractions" : 0 , "ListInteractions" : 0 , "AvgViewTimeSec" : null , "AvgSessionDurationMins" : 4.51935493548387 , "BounceRate" : 3.2258064516129 , "ViewsperSession" : 1.96774193548387 } , "SubRows" : { "APAC - Remote" : {  "attributes" : {  } , "measures" : { "Sessions" : 31 , "PageViews" : 61 , "SinglePageViewSessions" : 1 , "EntryPageSessions" : 31 , "DocumentInteractions" : 31 , "SocialInteractions" : 0 , "ListInteractions" : 0 , "AvgViewTimeSec" : null , "AvgSessionDurationMins" : 4.51935493548387 , "BounceRate" : 3.2258064516129 , "ViewsperSession" : 1.96774193548387 } , "SubRows" : { "Supply Chain Quality" : {  "attributes" : {  } , "measures" : { "Sessions" : 31 , "PageViews" : 61 , "SinglePageViewSessions" : 1 , "EntryPageSessions" : 31 , "DocumentInteractions" : 31 , "SocialInteractions" : 0 , "ListInteractions" : 0 , "AvgViewTimeSec" : null , "AvgSessionDurationMins" : 4.51935493548387 , "BounceRate" : 3.2258064516129 , "ViewsperSession" : 1.96774193548387 } , "SubRows" : { "Principal Quality Engineer" : {  "attributes" : {  } , "measures" : { "Sessions" : 31 , "PageViews" : 61 , "SinglePageViewSessions" : 1 , "EntryPageSessions" : 31 , "DocumentInteractions" : 31 , "SocialInteractions" : 0 , "ListInteractions" : 0 , "AvgViewTimeSec" : null , "AvgSessionDurationMins" : 4.51935493548387 , "BounceRate" : 3.2258064516129 , "ViewsperSession" : 1.96774193548387 } , "SubRows" : null }  } } } } } } } } } ] } ] }